[
  {
    "date": "",
    "market": "Wheat",
    "symbol": "001602",
    "report": "supplemental",
    "open_interest": 437771,
    "change_oi": 0,
    "change_spec_net": 0,
    "spekulanter": {
      "long": 0,
      "short": 0,
      "net": 0,
      "label": "Store Spekulanter"
    },
    "kommersielle": {
      "long": 0,
      "short": 0,
      "net": 0,
      "label": "Produsenter/Hedgers"
    },
    "indeksfond": {
      "long": 0,
      "short": 0,
      "net": 0,
      "label": "Indeksfond"
    },
    "smahandlere": {
      "long": 31366,
      "short": 50033,
      "net": -18667,
      "label": "Småhandlere"
    },
    "kategori": "landbruk",
    "navn_no": "Wheat",
    "forklaring": ""
  },
  {
    "date": "",
    "market": "Corn",
    "symbol": "002602",
    "report": "supplemental",
    "open_interest": 1247226,
    "change_oi": 0,
    "change_spec_net": 0,
    "spekulanter": {
      "long": 0,
      "short": 0,
      "net": 0,
      "label": "Store Spekulanter"
    },
    "kommersielle": {
      "long": 0,
      "short": 0,
      "net": 0,
      "label": "Produsenter/Hedgers"
    },
    "indeksfond": {
      "long": 0,
      "short": 0,
      "net": 0,
      "label": "Indeksfond"
    },
    "smahandlere": {
      "long": 127761,
      "short": 271200,
      "net": -143439,
      "label": "Småhandlere"
    },
    "kategori": "landbruk",
    "navn_no": "Mais",
    "forklaring": "Viktigste kornavling i USA."
  },
  {
    "date": "",
    "market": "Soybeans",
    "symbol": "005602",
    "report": "supplemental",
    "open_interest": 526575,
    "change_oi": 0,
    "change_spec_net": 0,
    "spekulanter": {
      "long": 0,
      "short": 0,
      "net": 0,
      "label": "Store Spekulanter"
    },
    "kommersielle": {
      "long": 0,
      "short": 0,
      "net": 0,
      "label": "Produsenter/Hedgers"
    },
    "indeksfond": {
      "long": 0,
      "short": 0,
      "net": 0,
      "label": "Indeksfond"
    },
    "smahandlere": {
      "long": 50651,
      "short": 91661,
      "net": -41010,
      "label": "Småhandlere"
    },
    "kategori": "landbruk",
    "navn_no": "Soyabønner",
    "forklaring": "Verdens nest viktigste kornavling."
  },
  {
    "date": "",
    "market": "Soybean Oil",
    "symbol": "007601",
    "report": "supplemental",
    "open_interest": 241324,
    "change_oi": 0,
    "change_spec_net": 0,
    "spekulanter": {
      "long": 0,
      "short": 0,
      "net": 0,
      "label": "Store Spekulanter"
    },
    "kommersielle": {
      "long": 0,
      "short": 0,
      "net": 0,
      "label": "Produsenter/Hedgers"
    },
    "indeksfond": {
      "long": 0,
      "short": 0,
      "net": 0,
      "label": "Indeksfond"
    },
    "smahandlere": {
      "long": 29969,
      "short": 19252,
      "net": 10717,
      "label": "Småhandlere"
    },
    "kategori": "landbruk",
    "navn_no": "Soybean Oil",
    "forklaring": ""
  },
  {
    "date": "",
    "market": "Cotton No. 2",
    "symbol": "033661",
    "report": "supplemental",
    "open_interest": 251292,
    "change_oi": 0,
    "change_spec_net": 0,
    "spekulanter": {
      "long": 0,
      "short": 0,
      "net": 0,
      "label": "Store Spekulanter"
    },
    "kommersielle": {
      "long": 0,
      "short": 0,
      "net": 0,
      "label": "Produsenter/Hedgers"
    },
    "indeksfond": {
      "long": 0,
      "short": 0,
      "net": 0,
      "label": "Indeksfond"
    },
    "smahandlere": {
      "long": 20614,
      "short": 7450,
      "net": 13164,
      "label": "Småhandlere"
    },
    "kategori": "landbruk",
    "navn_no": "Bomull",
    "forklaring": "Viktigste naturlige tekstilfiber."
  },
  {
    "date": "",
    "market": "Lean Hogs",
    "symbol": "054642",
    "report": "supplemental",
    "open_interest": 199052,
    "change_oi": 0,
    "change_spec_net": 0,
    "spekulanter": {
      "long": 0,
      "short": 0,
      "net": 0,
      "label": "Store Spekulanter"
    },
    "kommersielle": {
      "long": 0,
      "short": 0,
      "net": 0,
      "label": "Produsenter/Hedgers"
    },
    "indeksfond": {
      "long": 0,
      "short": 0,
      "net": 0,
      "label": "Indeksfond"
    },
    "smahandlere": {
      "long": 23361,
      "short": 33488,
      "net": -10127,
      "label": "Småhandlere"
    },
    "kategori": "landbruk",
    "navn_no": "Svinekjøtt",
    "forklaring": "Futures på mager svinekjøtt."
  },
  {
    "date": "",
    "market": "Live Cattle",
    "symbol": "057642",
    "report": "supplemental",
    "open_interest": 323347,
    "change_oi": 0,
    "change_spec_net": 0,
    "spekulanter": {
      "long": 0,
      "short": 0,
      "net": 0,
      "label": "Store Spekulanter"
    },
    "kommersielle": {
      "long": 0,
      "short": 0,
      "net": 0,
      "label": "Produsenter/Hedgers"
    },
    "indeksfond": {
      "long": 0,
      "short": 0,
      "net": 0,
      "label": "Indeksfond"
    },
    "smahandlere": {
      "long": 26092,
      "short": 58266,
      "net": -32174,
      "label": "Småhandlere"
    },
    "kategori": "landbruk",
    "navn_no": "Storfe",
    "forklaring": "Futures på levende storfe klar for slakt."
  },
  {
    "date": "",
    "market": "Feeder Cattle",
    "symbol": "061641",
    "report": "supplemental",
    "open_interest": 32245,
    "change_oi": 0,
    "change_spec_net": 0,
    "spekulanter": {
      "long": 0,
      "short": 0,
      "net": 0,
      "label": "Store Spekulanter"
    },
    "kommersielle": {
      "long": 0,
      "short": 0,
      "net": 0,
      "label": "Produsenter/Hedgers"
    },
    "indeksfond": {
      "long": 0,
      "short": 0,
      "net": 0,
      "label": "Indeksfond"
    },
    "smahandlere": {
      "long": 6292,
      "short": 11256,
      "net": -4964,
      "label": "Småhandlere"
    },
    "kategori": "landbruk",
    "navn_no": "Feeder Cattle",
    "forklaring": ""
  },
  {
    "date": "",
    "market": "Cocoa",
    "symbol": "073732",
    "report": "supplemental",
    "open_interest": 138563,
    "change_oi": 0,
    "change_spec_net": 0,
    "spekulanter": {
      "long": 0,
      "short": 0,
      "net": 0,
      "label": "Store Spekulanter"
    },
    "kommersielle": {
      "long": 0,
      "short": 0,
      "net": 0,
      "label": "Produsenter/Hedgers"
    },
    "indeksfond": {
      "long": 0,
      "short": 0,
      "net": 0,
      "label": "Indeksfond"
    },
    "smahandlere": {
      "long": 10190,
      "short": 4774,
      "net": 5416,
      "label": "Småhandlere"
    },
    "kategori": "landbruk",
    "navn_no": "Cocoa",
    "forklaring": ""
  },
  {
    "date": "",
    "market": "Sugar No. 11",
    "symbol": "080732",
    "report": "supplemental",
    "open_interest": 1269415,
    "change_oi": 0,
    "change_spec_net": 0,
    "spekulanter": {
      "long": 0,
      "short": 0,
      "net": 0,
      "label": "Store Spekulanter"
    },
    "kommersielle": {
      "long": 0,
      "short": 0,
      "net": 0,
      "label": "Produsenter/Hedgers"
    },
    "indeksfond": {
      "long": 0,
      "short": 0,
      "net": 0,
      "label": "Indeksfond"
    },
    "smahandlere": {
      "long": 100878,
      "short": 52222,
      "net": 48656,
      "label": "Småhandlere"
    },
    "kategori": "landbruk",
    "navn_no": "Sukker",
    "forklaring": "Råsukker. Viktig for mat og drivstoff."
  },
  {
    "date": "",
    "market": "Coffee C",
    "symbol": "083731",
    "report": "supplemental",
    "open_interest": 150969,
    "change_oi": 0,
    "change_spec_net": 0,
    "spekulanter": {
      "long": 0,
      "short": 0,
      "net": 0,
      "label": "Store Spekulanter"
    },
    "kommersielle": {
      "long": 0,
      "short": 0,
      "net": 0,
      "label": "Produsenter/Hedgers"
    },
    "indeksfond": {
      "long": 0,
      "short": 0,
      "net": 0,
      "label": "Indeksfond"
    },
    "smahandlere": {
      "long": 11677,
      "short": 7531,
      "net": 4146,
      "label": "Småhandlere"
    },
    "kategori": "landbruk",
    "navn_no": "Kaffe (Arabica)",
    "forklaring": "Arabica-kaffe handles på New York-børsen."
  }
]