[
  {
    "date": "2026-04-14",
    "market": "Canadian Dollar",
    "symbol": "090741",
    "report": "tff",
    "open_interest": 259258,
    "change_oi": 18523,
    "change_spec_net": -17260,
    "spekulanter": {
      "long": 22623,
      "short": 84027,
      "net": -61404,
      "label": "Hedge Funds"
    },
    "institusjoner": {
      "long": 68076,
      "short": 94586,
      "net": -26510,
      "label": "Pensjonsfond"
    },
    "meglere": {
      "long": 108148,
      "short": 32711,
      "net": 75437,
      "label": "Banker/Meglere"
    },
    "smahandlere": {
      "long": 30771,
      "short": 30876,
      "net": -105,
      "label": "Småhandlere"
    },
    "kategori": "valuta",
    "navn_no": "Kanadisk Dollar",
    "forklaring": "Tett knyttet til oljeprisen."
  },
  {
    "date": "2026-04-14",
    "market": "Swiss Franc",
    "symbol": "092741",
    "report": "tff",
    "open_interest": 93376,
    "change_oi": 6730,
    "change_spec_net": -3324,
    "spekulanter": {
      "long": 8828,
      "short": 12249,
      "net": -3421,
      "label": "Hedge Funds"
    },
    "institusjoner": {
      "long": 6293,
      "short": 47858,
      "net": -41565,
      "label": "Pensjonsfond"
    },
    "meglere": {
      "long": 61171,
      "short": 10574,
      "net": 50597,
      "label": "Banker/Meglere"
    },
    "smahandlere": {
      "long": 11511,
      "short": 18122,
      "net": -6611,
      "label": "Småhandlere"
    },
    "kategori": "valuta",
    "navn_no": "Sveitsisk Franc",
    "forklaring": "En av de sikreste valutaene i verden."
  },
  {
    "date": "2026-04-14",
    "market": "British Pound",
    "symbol": "096742",
    "report": "tff",
    "open_interest": 250053,
    "change_oi": 5862,
    "change_spec_net": -4202,
    "spekulanter": {
      "long": 54047,
      "short": 31716,
      "net": 22331,
      "label": "Hedge Funds"
    },
    "institusjoner": {
      "long": 36200,
      "short": 124115,
      "net": -87915,
      "label": "Pensjonsfond"
    },
    "meglere": {
      "long": 125770,
      "short": 56230,
      "net": 69540,
      "label": "Banker/Meglere"
    },
    "smahandlere": {
      "long": 24880,
      "short": 29404,
      "net": -4524,
      "label": "Småhandlere"
    },
    "kategori": "valuta",
    "navn_no": "Britisk Pund",
    "forklaring": "Påvirkes av Bank of England."
  },
  {
    "date": "2026-04-14",
    "market": "Japanese Yen",
    "symbol": "097741",
    "report": "tff",
    "open_interest": 354344,
    "change_oi": 4971,
    "change_spec_net": -3335,
    "spekulanter": {
      "long": 77737,
      "short": 132182,
      "net": -54445,
      "label": "Hedge Funds"
    },
    "institusjoner": {
      "long": 62664,
      "short": 72697,
      "net": -10033,
      "label": "Pensjonsfond"
    },
    "meglere": {
      "long": 66562,
      "short": 43133,
      "net": 23429,
      "label": "Banker/Meglere"
    },
    "smahandlere": {
      "long": 42124,
      "short": 39964,
      "net": 2160,
      "label": "Småhandlere"
    },
    "kategori": "valuta",
    "navn_no": "Japansk Yen",
    "forklaring": "Trygg-havn-valuta i urolige tider."
  },
  {
    "date": "2026-04-14",
    "market": "Euro Fx",
    "symbol": "099741",
    "report": "tff",
    "open_interest": 788828,
    "change_oi": 13785,
    "change_spec_net": 24500,
    "spekulanter": {
      "long": 117694,
      "short": 92312,
      "net": 25382,
      "label": "Hedge Funds"
    },
    "institusjoner": {
      "long": 434892,
      "short": 164450,
      "net": 270442,
      "label": "Pensjonsfond"
    },
    "meglere": {
      "long": 47901,
      "short": 385359,
      "net": -337458,
      "label": "Banker/Meglere"
    },
    "smahandlere": {
      "long": 84847,
      "short": 48333,
      "net": 36514,
      "label": "Småhandlere"
    },
    "kategori": "valuta",
    "navn_no": "Euro (EUR/USD)",
    "forklaring": "Verdens mest handlede valutapar."
  },
  {
    "date": "2026-04-14",
    "market": "Australian Dollar",
    "symbol": "232741",
    "report": "tff",
    "open_interest": 263918,
    "change_oi": -740,
    "change_spec_net": -2259,
    "spekulanter": {
      "long": 67142,
      "short": 23500,
      "net": 43642,
      "label": "Hedge Funds"
    },
    "institusjoner": {
      "long": 98320,
      "short": 61837,
      "net": 36483,
      "label": "Pensjonsfond"
    },
    "meglere": {
      "long": 41049,
      "short": 151875,
      "net": -110826,
      "label": "Banker/Meglere"
    },
    "smahandlere": {
      "long": 41421,
      "short": 15680,
      "net": 25741,
      "label": "Småhandlere"
    },
    "kategori": "valuta",
    "navn_no": "Australsk Dollar",
    "forklaring": "Råvarevaluta – følger kobber og jernmalm."
  },
  {
    "date": "2026-04-14",
    "market": "Euro Fx/British Pound Xrate",
    "symbol": "299741",
    "report": "tff",
    "open_interest": 34927,
    "change_oi": 248,
    "change_spec_net": -1052,
    "spekulanter": {
      "long": 2110,
      "short": 4373,
      "net": -2263,
      "label": "Hedge Funds"
    },
    "institusjoner": {
      "long": 17793,
      "short": 0,
      "net": 17793,
      "label": "Pensjonsfond"
    },
    "meglere": {
      "long": 0,
      "short": 24653,
      "net": -24653,
      "label": "Banker/Meglere"
    },
    "smahandlere": {
      "long": 13902,
      "short": 4779,
      "net": 9123,
      "label": "Småhandlere"
    },
    "kategori": "valuta",
    "navn_no": "Euro Fx/British Pound Xrate",
    "forklaring": ""
  },
  {
    "date": "2026-04-14",
    "market": "Euro Fx/Japanese Yen Xrate",
    "symbol": "399741",
    "report": "tff",
    "open_interest": 19941,
    "change_oi": 196,
    "change_spec_net": 469,
    "spekulanter": {
      "long": 1498,
      "short": 0,
      "net": 1498,
      "label": "Hedge Funds"
    },
    "institusjoner": {
      "long": 5456,
      "short": 12393,
      "net": -6937,
      "label": "Pensjonsfond"
    },
    "meglere": {
      "long": 3046,
      "short": 2173,
      "net": 873,
      "label": "Banker/Meglere"
    },
    "smahandlere": {
      "long": 9670,
      "short": 5104,
      "net": 4566,
      "label": "Småhandlere"
    },
    "kategori": "valuta",
    "navn_no": "Euro Fx/Japanese Yen Xrate",
    "forklaring": ""
  },
  {
    "date": "2026-04-14",
    "market": "Mexican Peso",
    "symbol": "095741",
    "report": "tff",
    "open_interest": 188147,
    "change_oi": 5357,
    "change_spec_net": -6262,
    "spekulanter": {
      "long": 73688,
      "short": 25344,
      "net": 48344,
      "label": "Hedge Funds"
    },
    "institusjoner": {
      "long": 81648,
      "short": 34607,
      "net": 47041,
      "label": "Pensjonsfond"
    },
    "meglere": {
      "long": 20737,
      "short": 48343,
      "net": -27606,
      "label": "Banker/Meglere"
    },
    "smahandlere": {
      "long": 8048,
      "short": 3422,
      "net": 4626,
      "label": "Småhandlere"
    },
    "kategori": "valuta",
    "navn_no": "Mexican Peso",
    "forklaring": ""
  },
  {
    "date": "2026-04-14",
    "market": "Brazilian Real",
    "symbol": "102741",
    "report": "tff",
    "open_interest": 130878,
    "change_oi": 16807,
    "change_spec_net": 2468,
    "spekulanter": {
      "long": 40873,
      "short": 38016,
      "net": 2857,
      "label": "Hedge Funds"
    },
    "institusjoner": {
      "long": 74022,
      "short": 1113,
      "net": 72909,
      "label": "Pensjonsfond"
    },
    "meglere": {
      "long": 5295,
      "short": 76169,
      "net": -70874,
      "label": "Banker/Meglere"
    },
    "smahandlere": {
      "long": 5168,
      "short": 1125,
      "net": 4043,
      "label": "Småhandlere"
    },
    "kategori": "valuta",
    "navn_no": "Brazilian Real",
    "forklaring": ""
  },
  {
    "date": "2026-04-14",
    "market": "Nz Dollar",
    "symbol": "112741",
    "report": "tff",
    "open_interest": 80727,
    "change_oi": 3775,
    "change_spec_net": -1266,
    "spekulanter": {
      "long": 6512,
      "short": 23603,
      "net": -17091,
      "label": "Hedge Funds"
    },
    "institusjoner": {
      "long": 7528,
      "short": 46047,
      "net": -38519,
      "label": "Pensjonsfond"
    },
    "meglere": {
      "long": 59616,
      "short": 5118,
      "net": 54498,
      "label": "Banker/Meglere"
    },
    "smahandlere": {
      "long": 3286,
      "short": 4722,
      "net": -1436,
      "label": "Småhandlere"
    },
    "kategori": "valuta",
    "navn_no": "New Zealand Dollar",
    "forklaring": "Barometer for global risikoappetitt."
  },
  {
    "date": "2026-04-14",
    "market": "So African Rand",
    "symbol": "122741",
    "report": "tff",
    "open_interest": 22450,
    "change_oi": -204,
    "change_spec_net": -2362,
    "spekulanter": {
      "long": 6761,
      "short": 2622,
      "net": 4139,
      "label": "Hedge Funds"
    },
    "institusjoner": {
      "long": 8958,
      "short": 628,
      "net": 8330,
      "label": "Pensjonsfond"
    },
    "meglere": {
      "long": 3295,
      "short": 17619,
      "net": -14324,
      "label": "Banker/Meglere"
    },
    "smahandlere": {
      "long": 2838,
      "short": 873,
      "net": 1965,
      "label": "Småhandlere"
    },
    "kategori": "valuta",
    "navn_no": "Sørafrikansk Rand",
    "forklaring": "Volatil valuta fra fremvoksende marked."
  },
  {
    "date": "2026-04-14",
    "market": "Djia Consolidated",
    "symbol": "12460+",
    "report": "tff",
    "open_interest": 72089,
    "change_oi": 3532,
    "change_spec_net": -4436,
    "spekulanter": {
      "long": 6350,
      "short": 18192,
      "net": -11842,
      "label": "Hedge Funds"
    },
    "institusjoner": {
      "long": 13171,
      "short": 7018,
      "net": 6153,
      "label": "Pensjonsfond"
    },
    "meglere": {
      "long": 34408,
      "short": 32098,
      "net": 2310,
      "label": "Banker/Meglere"
    },
    "smahandlere": {
      "long": 14012,
      "short": 10634,
      "net": 3378,
      "label": "Småhandlere"
    },
    "kategori": "annet",
    "navn_no": "Djia Consolidated",
    "forklaring": ""
  },
  {
    "date": "2026-04-14",
    "market": "Djia X $5",
    "symbol": "124603",
    "report": "tff",
    "open_interest": 68873,
    "change_oi": 316,
    "change_spec_net": -4768,
    "spekulanter": {
      "long": 6844,
      "short": 19018,
      "net": -12174,
      "label": "Hedge Funds"
    },
    "institusjoner": {
      "long": 13171,
      "short": 7018,
      "net": 6153,
      "label": "Pensjonsfond"
    },
    "meglere": {
      "long": 33426,
      "short": 32086,
      "net": 1340,
      "label": "Banker/Meglere"
    },
    "smahandlere": {
      "long": 13493,
      "short": 8812,
      "net": 4681,
      "label": "Småhandlere"
    },
    "kategori": "annet",
    "navn_no": "Djia X $5",
    "forklaring": ""
  },
  {
    "date": "2026-04-14",
    "market": "Dow Jones U.S. Real Estate Idx",
    "symbol": "124606",
    "report": "tff",
    "open_interest": 76377,
    "change_oi": 204,
    "change_spec_net": 1197,
    "spekulanter": {
      "long": 15997,
      "short": 7119,
      "net": 8878,
      "label": "Hedge Funds"
    },
    "institusjoner": {
      "long": 47392,
      "short": 7052,
      "net": 40340,
      "label": "Pensjonsfond"
    },
    "meglere": {
      "long": 6180,
      "short": 58615,
      "net": -52435,
      "label": "Banker/Meglere"
    },
    "smahandlere": {
      "long": 3960,
      "short": 743,
      "net": 3217,
      "label": "Småhandlere"
    },
    "kategori": "aksjer",
    "navn_no": "Dow Jones U.S. Real Estate Idx",
    "forklaring": ""
  },
  {
    "date": "2026-04-14",
    "market": "Micro E",
    "symbol": "124608",
    "report": "tff",
    "open_interest": 32163,
    "change_oi": 0,
    "change_spec_net": 0,
    "spekulanter": {
      "long": 12446,
      "short": 9123,
      "net": 3323,
      "label": "Hedge Funds"
    },
    "institusjoner": {
      "long": 0,
      "short": 0,
      "net": 0,
      "label": "Pensjonsfond"
    },
    "meglere": {
      "long": 13906,
      "short": 4200,
      "net": 9706,
      "label": "Banker/Meglere"
    },
    "smahandlere": {
      "long": 5193,
      "short": 18222,
      "net": -13029,
      "label": "Småhandlere"
    },
    "kategori": "annet",
    "navn_no": "Micro E",
    "forklaring": ""
  },
  {
    "date": "2026-04-14",
    "market": "S&P 500 Consolidated",
    "symbol": "13874+",
    "report": "tff",
    "open_interest": 1980961,
    "change_oi": 32619,
    "change_spec_net": -173651,
    "spekulanter": {
      "long": 124232,
      "short": 538757,
      "net": -414525,
      "label": "Hedge Funds"
    },
    "institusjoner": {
      "long": 1205193,
      "short": 198055,
      "net": 1007138,
      "label": "Pensjonsfond"
    },
    "meglere": {
      "long": 133178,
      "short": 829910,
      "net": -696732,
      "label": "Banker/Meglere"
    },
    "smahandlere": {
      "long": 248873,
      "short": 185106,
      "net": 63767,
      "label": "Småhandlere"
    },
    "kategori": "aksjer",
    "navn_no": "S&P 500",
    "forklaring": "De 500 største selskapene i USA."
  },
  {
    "date": "2026-04-14",
    "market": "E",
    "symbol": "138748",
    "report": "tff",
    "open_interest": 27510,
    "change_oi": 5023,
    "change_spec_net": 3536,
    "spekulanter": {
      "long": 2776,
      "short": 986,
      "net": 1790,
      "label": "Hedge Funds"
    },
    "institusjoner": {
      "long": 3731,
      "short": 20131,
      "net": -16400,
      "label": "Pensjonsfond"
    },
    "meglere": {
      "long": 18561,
      "short": 4566,
      "net": 13995,
      "label": "Banker/Meglere"
    },
    "smahandlere": {
      "long": 2260,
      "short": 1645,
      "net": 615,
      "label": "Småhandlere"
    },
    "kategori": "aksjer",
    "navn_no": "E",
    "forklaring": ""
  },
  {
    "date": "2026-04-14",
    "market": "Adjusted Int Rate S&P 500 Totl",
    "symbol": "13874W",
    "report": "tff",
    "open_interest": 852155,
    "change_oi": -7340,
    "change_spec_net": -19796,
    "spekulanter": {
      "long": 118458,
      "short": 101989,
      "net": 16469,
      "label": "Hedge Funds"
    },
    "institusjoner": {
      "long": 1634,
      "short": 131722,
      "net": -130088,
      "label": "Pensjonsfond"
    },
    "meglere": {
      "long": 306165,
      "short": 186685,
      "net": 119480,
      "label": "Banker/Meglere"
    },
    "smahandlere": {
      "long": 6229,
      "short": 12090,
      "net": -5861,
      "label": "Småhandlere"
    },
    "kategori": "aksjer",
    "navn_no": "Adjusted Int Rate S&P 500 Totl",
    "forklaring": ""
  },
  {
    "date": "2026-04-14",
    "market": "Nasdaq",
    "symbol": "20974+",
    "report": "tff",
    "open_interest": 276532,
    "change_oi": 17869,
    "change_spec_net": -13858,
    "spekulanter": {
      "long": 41041,
      "short": 99933,
      "net": -58892,
      "label": "Hedge Funds"
    },
    "institusjoner": {
      "long": 107107,
      "short": 29810,
      "net": 77297,
      "label": "Pensjonsfond"
    },
    "meglere": {
      "long": 53045,
      "short": 76659,
      "net": -23614,
      "label": "Banker/Meglere"
    },
    "smahandlere": {
      "long": 38371,
      "short": 38699,
      "net": -328,
      "label": "Småhandlere"
    },
    "kategori": "aksjer",
    "navn_no": "Nasdaq 100",
    "forklaring": "Teknologiindeks. Apple, Microsoft, Nvidia m.fl."
  },
  {
    "date": "2026-04-14",
    "market": "Nasdaq Mini",
    "symbol": "209742",
    "report": "tff",
    "open_interest": 260197,
    "change_oi": 13403,
    "change_spec_net": -10839,
    "spekulanter": {
      "long": 44471,
      "short": 94138,
      "net": -49667,
      "label": "Hedge Funds"
    },
    "institusjoner": {
      "long": 106090,
      "short": 29785,
      "net": 76305,
      "label": "Pensjonsfond"
    },
    "meglere": {
      "long": 51423,
      "short": 83979,
      "net": -32556,
      "label": "Banker/Meglere"
    },
    "smahandlere": {
      "long": 34416,
      "short": 34136,
      "net": 280,
      "label": "Småhandlere"
    },
    "kategori": "aksjer",
    "navn_no": "Nasdaq Mini",
    "forklaring": "Mindre Nasdaq-kontrakt."
  },
  {
    "date": "2026-04-14",
    "market": "Russell E",
    "symbol": "239742",
    "report": "tff",
    "open_interest": 404501,
    "change_oi": 7063,
    "change_spec_net": -13990,
    "spekulanter": {
      "long": 72144,
      "short": 122880,
      "net": -50736,
      "label": "Hedge Funds"
    },
    "institusjoner": {
      "long": 147210,
      "short": 129319,
      "net": 17891,
      "label": "Pensjonsfond"
    },
    "meglere": {
      "long": 116339,
      "short": 81667,
      "net": 34672,
      "label": "Banker/Meglere"
    },
    "smahandlere": {
      "long": 25893,
      "short": 23249,
      "net": 2644,
      "label": "Småhandlere"
    },
    "kategori": "aksjer",
    "navn_no": "Russell 2000",
    "forklaring": "2000 mindre amerikanske selskaper."
  },
  {
    "date": "2026-04-07",
    "market": "Emini Russell 1000 Value Index",
    "symbol": "239744",
    "report": "tff",
    "open_interest": 32439,
    "change_oi": -521,
    "change_spec_net": 0,
    "spekulanter": {
      "long": 0,
      "short": 0,
      "net": 0,
      "label": "Hedge Funds"
    },
    "institusjoner": {
      "long": 8928,
      "short": 18176,
      "net": -9248,
      "label": "Pensjonsfond"
    },
    "meglere": {
      "long": 21423,
      "short": 13289,
      "net": 8134,
      "label": "Banker/Meglere"
    },
    "smahandlere": {
      "long": 2088,
      "short": 974,
      "net": 1114,
      "label": "Småhandlere"
    },
    "kategori": "aksjer",
    "navn_no": "Emini Russell 1000 Value Index",
    "forklaring": ""
  },
  {
    "date": "2026-03-03",
    "market": "Nikkei Stock Average",
    "symbol": "240741",
    "report": "tff",
    "open_interest": 11702,
    "change_oi": 0,
    "change_spec_net": 0,
    "spekulanter": {
      "long": 205,
      "short": 1490,
      "net": -1285,
      "label": "Hedge Funds"
    },
    "institusjoner": {
      "long": 6068,
      "short": 575,
      "net": 5493,
      "label": "Pensjonsfond"
    },
    "meglere": {
      "long": 497,
      "short": 7779,
      "net": -7282,
      "label": "Banker/Meglere"
    },
    "smahandlere": {
      "long": 3168,
      "short": 1839,
      "net": 1329,
      "label": "Småhandlere"
    },
    "kategori": "aksjer",
    "navn_no": "Nikkei (Japan)",
    "forklaring": "225 største selskaper på Tokyo-børsen."
  },
  {
    "date": "2026-04-14",
    "market": "Nikkei Stock Average Yen Denom",
    "symbol": "240743",
    "report": "tff",
    "open_interest": 34012,
    "change_oi": 2349,
    "change_spec_net": 274,
    "spekulanter": {
      "long": 12203,
      "short": 4000,
      "net": 8203,
      "label": "Hedge Funds"
    },
    "institusjoner": {
      "long": 7654,
      "short": 1878,
      "net": 5776,
      "label": "Pensjonsfond"
    },
    "meglere": {
      "long": 7259,
      "short": 7306,
      "net": -47,
      "label": "Banker/Meglere"
    },
    "smahandlere": {
      "long": 6121,
      "short": 20053,
      "net": -13932,
      "label": "Småhandlere"
    },
    "kategori": "aksjer",
    "navn_no": "Nikkei Stock Average Yen Denom",
    "forklaring": ""
  },
  {
    "date": "2026-04-14",
    "market": "Msci Eafe",
    "symbol": "244041",
    "report": "tff",
    "open_interest": 460246,
    "change_oi": -31102,
    "change_spec_net": 29346,
    "spekulanter": {
      "long": 39315,
      "short": 38500,
      "net": 815,
      "label": "Hedge Funds"
    },
    "institusjoner": {
      "long": 304708,
      "short": 71705,
      "net": 233003,
      "label": "Pensjonsfond"
    },
    "meglere": {
      "long": 39580,
      "short": 280106,
      "net": -240526,
      "label": "Banker/Meglere"
    },
    "smahandlere": {
      "long": 13054,
      "short": 6811,
      "net": 6243,
      "label": "Småhandlere"
    },
    "kategori": "aksjer",
    "navn_no": "MSCI Europa/Asia",
    "forklaring": "Aksjer utenfor USA: Europa, Japan, Australia."
  },
  {
    "date": "2026-04-14",
    "market": "Msci Em Index",
    "symbol": "244042",
    "report": "tff",
    "open_interest": 1116058,
    "change_oi": -11391,
    "change_spec_net": 2478,
    "spekulanter": {
      "long": 143282,
      "short": 132017,
      "net": 11265,
      "label": "Hedge Funds"
    },
    "institusjoner": {
      "long": 731137,
      "short": 221476,
      "net": 509661,
      "label": "Pensjonsfond"
    },
    "meglere": {
      "long": 73148,
      "short": 616474,
      "net": -543326,
      "label": "Banker/Meglere"
    },
    "smahandlere": {
      "long": 35853,
      "short": 7798,
      "net": 28055,
      "label": "Småhandlere"
    },
    "kategori": "aksjer",
    "navn_no": "MSCI Fremvoksende",
    "forklaring": "Kina, India, Brasil og andre vekstmarkeder."
  },
  {
    "date": "2026-04-14",
    "market": "S&P 500 Annual Dividend Index",
    "symbol": "43874A",
    "report": "tff",
    "open_interest": 358877,
    "change_oi": 7750,
    "change_spec_net": 3196,
    "spekulanter": {
      "long": 172285,
      "short": 11914,
      "net": 160371,
      "label": "Hedge Funds"
    },
    "institusjoner": {
      "long": 94802,
      "short": 13991,
      "net": 80811,
      "label": "Pensjonsfond"
    },
    "meglere": {
      "long": 33949,
      "short": 275944,
      "net": -241995,
      "label": "Banker/Meglere"
    },
    "smahandlere": {
      "long": 3685,
      "short": 3554,
      "net": 131,
      "label": "Småhandlere"
    },
    "kategori": "aksjer",
    "navn_no": "S&P 500 Annual Dividend Index",
    "forklaring": ""
  },
  {
    "date": "2026-04-14",
    "market": "S&P 500 Quarterly Dividend Ind",
    "symbol": "43874Q",
    "report": "tff",
    "open_interest": 41384,
    "change_oi": 1391,
    "change_spec_net": 313,
    "spekulanter": {
      "long": 30955,
      "short": 21136,
      "net": 9819,
      "label": "Hedge Funds"
    },
    "institusjoner": {
      "long": 1008,
      "short": 0,
      "net": 1008,
      "label": "Pensjonsfond"
    },
    "meglere": {
      "long": 3106,
      "short": 13948,
      "net": -10842,
      "label": "Banker/Meglere"
    },
    "smahandlere": {
      "long": 20,
      "short": 5,
      "net": 15,
      "label": "Småhandlere"
    },
    "kategori": "aksjer",
    "navn_no": "S&P 500 Quarterly Dividend Ind",
    "forklaring": ""
  },
  {
    "date": "2026-04-14",
    "market": "Ust Bond",
    "symbol": "020601",
    "report": "tff",
    "open_interest": 1778844,
    "change_oi": -7670,
    "change_spec_net": -20657,
    "spekulanter": {
      "long": 122261,
      "short": 327779,
      "net": -205518,
      "label": "Hedge Funds"
    },
    "institusjoner": {
      "long": 1061713,
      "short": 683546,
      "net": 378167,
      "label": "Pensjonsfond"
    },
    "meglere": {
      "long": 20790,
      "short": 290138,
      "net": -269348,
      "label": "Banker/Meglere"
    },
    "smahandlere": {
      "long": 228604,
      "short": 123716,
      "net": 104888,
      "label": "Småhandlere"
    },
    "kategori": "renter",
    "navn_no": "USA 30-årig rente",
    "forklaring": "Langsiktig rente for pensjonsfond."
  },
  {
    "date": "2026-04-14",
    "market": "Ultra Ust Bond",
    "symbol": "020604",
    "report": "tff",
    "open_interest": 2279418,
    "change_oi": 17441,
    "change_spec_net": -35757,
    "spekulanter": {
      "long": 54276,
      "short": 951628,
      "net": -897352,
      "label": "Hedge Funds"
    },
    "institusjoner": {
      "long": 1589875,
      "short": 394304,
      "net": 1195571,
      "label": "Pensjonsfond"
    },
    "meglere": {
      "long": 12527,
      "short": 329338,
      "net": -316811,
      "label": "Banker/Meglere"
    },
    "smahandlere": {
      "long": 187419,
      "short": 182470,
      "net": 4949,
      "label": "Småhandlere"
    },
    "kategori": "renter",
    "navn_no": "Ultra Ust Bond",
    "forklaring": ""
  },
  {
    "date": "2026-04-14",
    "market": "Ust 2Y Note",
    "symbol": "042601",
    "report": "tff",
    "open_interest": 4697992,
    "change_oi": -7613,
    "change_spec_net": 68629,
    "spekulanter": {
      "long": 396501,
      "short": 2475701,
      "net": -2079200,
      "label": "Hedge Funds"
    },
    "institusjoner": {
      "long": 2972695,
      "short": 611793,
      "net": 2360902,
      "label": "Pensjonsfond"
    },
    "meglere": {
      "long": 113542,
      "short": 580515,
      "net": -466973,
      "label": "Banker/Meglere"
    },
    "smahandlere": {
      "long": 222693,
      "short": 144697,
      "net": 77996,
      "label": "Småhandlere"
    },
    "kategori": "renter",
    "navn_no": "USA 2-årig rente",
    "forklaring": "Sensitiv for hva sentralbanken (Fed) gjør."
  },
  {
    "date": "2026-04-14",
    "market": "Ust 10Y Note",
    "symbol": "043602",
    "report": "tff",
    "open_interest": 5187440,
    "change_oi": 64318,
    "change_spec_net": -34286,
    "spekulanter": {
      "long": 328463,
      "short": 2338434,
      "net": -2009971,
      "label": "Hedge Funds"
    },
    "institusjoner": {
      "long": 3049475,
      "short": 836218,
      "net": 2213257,
      "label": "Pensjonsfond"
    },
    "meglere": {
      "long": 206647,
      "short": 601050,
      "net": -394403,
      "label": "Banker/Meglere"
    },
    "smahandlere": {
      "long": 405706,
      "short": 363298,
      "net": 42408,
      "label": "Småhandlere"
    },
    "kategori": "renter",
    "navn_no": "USA 10-årig rente",
    "forklaring": "Viktigste globale rente. Påvirker boliglån verden over."
  },
  {
    "date": "2026-04-14",
    "market": "Ultra Ust 10Y",
    "symbol": "043607",
    "report": "tff",
    "open_interest": 2392800,
    "change_oi": 31951,
    "change_spec_net": 40566,
    "spekulanter": {
      "long": 121936,
      "short": 411264,
      "net": -289328,
      "label": "Hedge Funds"
    },
    "institusjoner": {
      "long": 1293621,
      "short": 569833,
      "net": 723788,
      "label": "Pensjonsfond"
    },
    "meglere": {
      "long": 23862,
      "short": 367673,
      "net": -343811,
      "label": "Banker/Meglere"
    },
    "smahandlere": {
      "long": 209565,
      "short": 327386,
      "net": -117821,
      "label": "Småhandlere"
    },
    "kategori": "renter",
    "navn_no": "Ultra Ust 10Y",
    "forklaring": ""
  },
  {
    "date": "2026-03-31",
    "market": "Micro 10 Year Yield",
    "symbol": "04360Y",
    "report": "tff",
    "open_interest": 2712,
    "change_oi": 291,
    "change_spec_net": -438,
    "spekulanter": {
      "long": 1045,
      "short": 334,
      "net": 711,
      "label": "Hedge Funds"
    },
    "institusjoner": {
      "long": 0,
      "short": 0,
      "net": 0,
      "label": "Pensjonsfond"
    },
    "meglere": {
      "long": 0,
      "short": 0,
      "net": 0,
      "label": "Banker/Meglere"
    },
    "smahandlere": {
      "long": 474,
      "short": 830,
      "net": -356,
      "label": "Småhandlere"
    },
    "kategori": "annet",
    "navn_no": "Micro 10 Year Yield",
    "forklaring": ""
  },
  {
    "date": "2026-04-14",
    "market": "Ust 5Y Note",
    "symbol": "044601",
    "report": "tff",
    "open_interest": 6495803,
    "change_oi": 50624,
    "change_spec_net": -15039,
    "spekulanter": {
      "long": 532791,
      "short": 2987909,
      "net": -2455118,
      "label": "Hedge Funds"
    },
    "institusjoner": {
      "long": 3860963,
      "short": 996285,
      "net": 2864678,
      "label": "Pensjonsfond"
    },
    "meglere": {
      "long": 106776,
      "short": 806934,
      "net": -700158,
      "label": "Banker/Meglere"
    },
    "smahandlere": {
      "long": 397241,
      "short": 326780,
      "net": 70461,
      "label": "Småhandlere"
    },
    "kategori": "renter",
    "navn_no": "USA 5-årig rente",
    "forklaring": "Mellomlang amerikansk statsrente."
  },
  {
    "date": "2026-04-14",
    "market": "Fed Funds",
    "symbol": "045601",
    "report": "tff",
    "open_interest": 1857369,
    "change_oi": 17103,
    "change_spec_net": 66339,
    "spekulanter": {
      "long": 450647,
      "short": 283738,
      "net": 166909,
      "label": "Hedge Funds"
    },
    "institusjoner": {
      "long": 42733,
      "short": 120180,
      "net": -77447,
      "label": "Pensjonsfond"
    },
    "meglere": {
      "long": 334460,
      "short": 445424,
      "net": -110964,
      "label": "Banker/Meglere"
    },
    "smahandlere": {
      "long": 47911,
      "short": 33308,
      "net": 14603,
      "label": "Småhandlere"
    },
    "kategori": "annet",
    "navn_no": "Fed Funds",
    "forklaring": ""
  },
  {
    "date": "2026-04-14",
    "market": "Euro Short Term Rate",
    "symbol": "047745",
    "report": "tff",
    "open_interest": 14001,
    "change_oi": -31,
    "change_spec_net": -1012,
    "spekulanter": {
      "long": 1074,
      "short": 529,
      "net": 545,
      "label": "Hedge Funds"
    },
    "institusjoner": {
      "long": 350,
      "short": 715,
      "net": -365,
      "label": "Pensjonsfond"
    },
    "meglere": {
      "long": 6912,
      "short": 7451,
      "net": -539,
      "label": "Banker/Meglere"
    },
    "smahandlere": {
      "long": 43,
      "short": 7,
      "net": 36,
      "label": "Småhandlere"
    },
    "kategori": "annet",
    "navn_no": "Euro Short Term Rate",
    "forklaring": ""
  },
  {
    "date": "2026-04-14",
    "market": "Sofr",
    "symbol": "134741",
    "report": "tff",
    "open_interest": 12033346,
    "change_oi": -22172,
    "change_spec_net": -157345,
    "spekulanter": {
      "long": 1574647,
      "short": 2357979,
      "net": -783332,
      "label": "Hedge Funds"
    },
    "institusjoner": {
      "long": 1063582,
      "short": 1027864,
      "net": 35718,
      "label": "Pensjonsfond"
    },
    "meglere": {
      "long": 3057534,
      "short": 2360586,
      "net": 696948,
      "label": "Banker/Meglere"
    },
    "smahandlere": {
      "long": 34441,
      "short": 33922,
      "net": 519,
      "label": "Småhandlere"
    },
    "kategori": "renter",
    "navn_no": "SOFR (dagslånsrente)",
    "forklaring": "Hva banker betaler for korte dollarlån."
  },
  {
    "date": "2026-04-14",
    "market": "Bbg Commodity",
    "symbol": "221602",
    "report": "tff",
    "open_interest": 241044,
    "change_oi": 4245,
    "change_spec_net": 3199,
    "spekulanter": {
      "long": 7734,
      "short": 4351,
      "net": 3383,
      "label": "Hedge Funds"
    },
    "institusjoner": {
      "long": 99583,
      "short": 901,
      "net": 98682,
      "label": "Pensjonsfond"
    },
    "meglere": {
      "long": 129558,
      "short": 233484,
      "net": -103926,
      "label": "Banker/Meglere"
    },
    "smahandlere": {
      "long": 589,
      "short": 16,
      "net": 573,
      "label": "Småhandlere"
    },
    "kategori": "annet",
    "navn_no": "Bbg Commodity",
    "forklaring": ""
  },
  {
    "date": "2026-04-07",
    "market": "Bloomberg Hy Credit Futures",
    "symbol": "221605",
    "report": "tff",
    "open_interest": 1808,
    "change_oi": -19,
    "change_spec_net": -269,
    "spekulanter": {
      "long": 395,
      "short": 678,
      "net": -283,
      "label": "Hedge Funds"
    },
    "institusjoner": {
      "long": 987,
      "short": 695,
      "net": 292,
      "label": "Pensjonsfond"
    },
    "meglere": {
      "long": 333,
      "short": 130,
      "net": 203,
      "label": "Banker/Meglere"
    },
    "smahandlere": {
      "long": 52,
      "short": 29,
      "net": 23,
      "label": "Småhandlere"
    },
    "kategori": "annet",
    "navn_no": "Bloomberg Hy Credit Futures",
    "forklaring": ""
  },
  {
    "date": "2026-04-14",
    "market": "2 Year Eris Sofr Swap",
    "symbol": "342603",
    "report": "tff",
    "open_interest": 105974,
    "change_oi": -4379,
    "change_spec_net": -4140,
    "spekulanter": {
      "long": 9425,
      "short": 32185,
      "net": -22760,
      "label": "Hedge Funds"
    },
    "institusjoner": {
      "long": 57250,
      "short": 11607,
      "net": 45643,
      "label": "Pensjonsfond"
    },
    "meglere": {
      "long": 3742,
      "short": 4695,
      "net": -953,
      "label": "Banker/Meglere"
    },
    "smahandlere": {
      "long": 0,
      "short": 4,
      "net": -4,
      "label": "Småhandlere"
    },
    "kategori": "renter",
    "navn_no": "2 Year Eris Sofr Swap",
    "forklaring": ""
  },
  {
    "date": "2026-04-14",
    "market": "10 Year Eris Sofr Swap",
    "symbol": "343603",
    "report": "tff",
    "open_interest": 230890,
    "change_oi": 1491,
    "change_spec_net": -2228,
    "spekulanter": {
      "long": 8270,
      "short": 158569,
      "net": -150299,
      "label": "Hedge Funds"
    },
    "institusjoner": {
      "long": 26831,
      "short": 5661,
      "net": 21170,
      "label": "Pensjonsfond"
    },
    "meglere": {
      "long": 27730,
      "short": 8970,
      "net": 18760,
      "label": "Banker/Meglere"
    },
    "smahandlere": {
      "long": 1,
      "short": 18,
      "net": -17,
      "label": "Småhandlere"
    },
    "kategori": "renter",
    "navn_no": "10 Year Eris Sofr Swap",
    "forklaring": ""
  },
  {
    "date": "2026-04-14",
    "market": "5 Year Eris Sofr Swap",
    "symbol": "344605",
    "report": "tff",
    "open_interest": 198187,
    "change_oi": 4033,
    "change_spec_net": -1250,
    "spekulanter": {
      "long": 6092,
      "short": 75978,
      "net": -69886,
      "label": "Hedge Funds"
    },
    "institusjoner": {
      "long": 40944,
      "short": 34410,
      "net": 6534,
      "label": "Pensjonsfond"
    },
    "meglere": {
      "long": 33068,
      "short": 5932,
      "net": 27136,
      "label": "Banker/Meglere"
    },
    "smahandlere": {
      "long": 10,
      "short": 67,
      "net": -57,
      "label": "Småhandlere"
    },
    "kategori": "renter",
    "navn_no": "5 Year Eris Sofr Swap",
    "forklaring": ""
  },
  {
    "date": "2026-04-14",
    "market": "3 Year Eris Sofr Swap",
    "symbol": "344606",
    "report": "tff",
    "open_interest": 94873,
    "change_oi": -903,
    "change_spec_net": -486,
    "spekulanter": {
      "long": 750,
      "short": 35510,
      "net": -34760,
      "label": "Hedge Funds"
    },
    "institusjoner": {
      "long": 74000,
      "short": 4324,
      "net": 69676,
      "label": "Pensjonsfond"
    },
    "meglere": {
      "long": 0,
      "short": 27760,
      "net": -27760,
      "label": "Banker/Meglere"
    },
    "smahandlere": {
      "long": 20,
      "short": 21,
      "net": -1,
      "label": "Småhandlere"
    },
    "kategori": "renter",
    "navn_no": "3 Year Eris Sofr Swap",
    "forklaring": ""
  },
  {
    "date": "2026-04-14",
    "market": "7 Year Eris Sofr Swap",
    "symbol": "344607",
    "report": "tff",
    "open_interest": 37008,
    "change_oi": -291,
    "change_spec_net": 8,
    "spekulanter": {
      "long": 5338,
      "short": 996,
      "net": 4342,
      "label": "Hedge Funds"
    },
    "institusjoner": {
      "long": 9000,
      "short": 4460,
      "net": 4540,
      "label": "Pensjonsfond"
    },
    "meglere": {
      "long": 3494,
      "short": 14361,
      "net": -10867,
      "label": "Banker/Meglere"
    },
    "smahandlere": {
      "long": 13,
      "short": 16,
      "net": -3,
      "label": "Småhandlere"
    },
    "kategori": "renter",
    "navn_no": "7 Year Eris Sofr Swap",
    "forklaring": ""
  },
  {
    "date": "2026-04-14",
    "market": "Micro Bitcoin",
    "symbol": "133742",
    "report": "tff",
    "open_interest": 23473,
    "change_oi": 1627,
    "change_spec_net": -2343,
    "spekulanter": {
      "long": 8794,
      "short": 7534,
      "net": 1260,
      "label": "Hedge Funds"
    },
    "institusjoner": {
      "long": 524,
      "short": 1264,
      "net": -740,
      "label": "Pensjonsfond"
    },
    "meglere": {
      "long": 777,
      "short": 6733,
      "net": -5956,
      "label": "Banker/Meglere"
    },
    "smahandlere": {
      "long": 5984,
      "short": 2293,
      "net": 3691,
      "label": "Småhandlere"
    },
    "kategori": "krypto",
    "navn_no": "Micro Bitcoin",
    "forklaring": ""
  },
  {
    "date": "2026-04-14",
    "market": "Nano Bitcoin",
    "symbol": "133LM1",
    "report": "tff",
    "open_interest": 41171,
    "change_oi": 8076,
    "change_spec_net": 2276,
    "spekulanter": {
      "long": 21295,
      "short": 20560,
      "net": 735,
      "label": "Hedge Funds"
    },
    "institusjoner": {
      "long": 0,
      "short": 0,
      "net": 0,
      "label": "Pensjonsfond"
    },
    "meglere": {
      "long": 0,
      "short": 0,
      "net": 0,
      "label": "Banker/Meglere"
    },
    "smahandlere": {
      "long": 1551,
      "short": 1387,
      "net": 164,
      "label": "Småhandlere"
    },
    "kategori": "krypto",
    "navn_no": "Bitcoin Mini",
    "forklaring": "Mindre Bitcoin-kontrakt (1/100 BTC)."
  },
  {
    "date": "2026-04-14",
    "market": "Nano Bitcoin Perp Style",
    "symbol": "133LM4",
    "report": "tff",
    "open_interest": 205954,
    "change_oi": 49133,
    "change_spec_net": 47856,
    "spekulanter": {
      "long": 120243,
      "short": 41455,
      "net": 78788,
      "label": "Hedge Funds"
    },
    "institusjoner": {
      "long": 0,
      "short": 0,
      "net": 0,
      "label": "Pensjonsfond"
    },
    "meglere": {
      "long": 0,
      "short": 725,
      "net": -725,
      "label": "Banker/Meglere"
    },
    "smahandlere": {
      "long": 10859,
      "short": 7829,
      "net": 3030,
      "label": "Småhandlere"
    },
    "kategori": "krypto",
    "navn_no": "Bitcoin Mini Perp",
    "forklaring": "Bitcoin uten utløpsdato."
  },
  {
    "date": "2026-03-31",
    "market": "Bitcoin Cash Perp Style",
    "symbol": "133LM5",
    "report": "tff",
    "open_interest": 2634,
    "change_oi": 0,
    "change_spec_net": 0,
    "spekulanter": {
      "long": 1621,
      "short": 2313,
      "net": -692,
      "label": "Hedge Funds"
    },
    "institusjoner": {
      "long": 0,
      "short": 0,
      "net": 0,
      "label": "Pensjonsfond"
    },
    "meglere": {
      "long": 0,
      "short": 0,
      "net": 0,
      "label": "Banker/Meglere"
    },
    "smahandlere": {
      "long": 198,
      "short": 67,
      "net": 131,
      "label": "Småhandlere"
    },
    "kategori": "krypto",
    "navn_no": "Bitcoin Cash Perp Style",
    "forklaring": ""
  },
  {
    "date": "2026-04-14",
    "market": "Micro Ether",
    "symbol": "146022",
    "report": "tff",
    "open_interest": 61243,
    "change_oi": -668,
    "change_spec_net": -6942,
    "spekulanter": {
      "long": 27322,
      "short": 46445,
      "net": -19123,
      "label": "Hedge Funds"
    },
    "institusjoner": {
      "long": 2137,
      "short": 7448,
      "net": -5311,
      "label": "Pensjonsfond"
    },
    "meglere": {
      "long": 1593,
      "short": 0,
      "net": 1593,
      "label": "Banker/Meglere"
    },
    "smahandlere": {
      "long": 2089,
      "short": 864,
      "net": 1225,
      "label": "Småhandlere"
    },
    "kategori": "krypto",
    "navn_no": "Micro Ether",
    "forklaring": ""
  },
  {
    "date": "2026-04-14",
    "market": "Nano Ether",
    "symbol": "146LM1",
    "report": "tff",
    "open_interest": 40328,
    "change_oi": -2635,
    "change_spec_net": -9228,
    "spekulanter": {
      "long": 3494,
      "short": 28406,
      "net": -24912,
      "label": "Hedge Funds"
    },
    "institusjoner": {
      "long": 0,
      "short": 0,
      "net": 0,
      "label": "Pensjonsfond"
    },
    "meglere": {
      "long": 0,
      "short": 0,
      "net": 0,
      "label": "Banker/Meglere"
    },
    "smahandlere": {
      "long": 800,
      "short": 664,
      "net": 136,
      "label": "Småhandlere"
    },
    "kategori": "krypto",
    "navn_no": "Ethereum Mini",
    "forklaring": "Ethereum – plattform for smarte kontrakter."
  },
  {
    "date": "2026-04-14",
    "market": "Nano Ether Perp Style",
    "symbol": "146LM3",
    "report": "tff",
    "open_interest": 194616,
    "change_oi": 37554,
    "change_spec_net": 79679,
    "spekulanter": {
      "long": 78467,
      "short": 36108,
      "net": 42359,
      "label": "Hedge Funds"
    },
    "institusjoner": {
      "long": 0,
      "short": 0,
      "net": 0,
      "label": "Pensjonsfond"
    },
    "meglere": {
      "long": 0,
      "short": 437,
      "net": -437,
      "label": "Banker/Meglere"
    },
    "smahandlere": {
      "long": 8690,
      "short": 4083,
      "net": 4607,
      "label": "Småhandlere"
    },
    "kategori": "krypto",
    "navn_no": "Ethereum Mini Perp",
    "forklaring": "Ethereum uten utløpsdato."
  },
  {
    "date": "2026-01-27",
    "market": "Litecoin Cash",
    "symbol": "167LM0",
    "report": "tff",
    "open_interest": 1454,
    "change_oi": 7,
    "change_spec_net": -125,
    "spekulanter": {
      "long": 0,
      "short": 833,
      "net": -833,
      "label": "Hedge Funds"
    },
    "institusjoner": {
      "long": 0,
      "short": 0,
      "net": 0,
      "label": "Pensjonsfond"
    },
    "meglere": {
      "long": 0,
      "short": 0,
      "net": 0,
      "label": "Banker/Meglere"
    },
    "smahandlere": {
      "long": 296,
      "short": 92,
      "net": 204,
      "label": "Småhandlere"
    },
    "kategori": "krypto",
    "navn_no": "Litecoin Cash",
    "forklaring": ""
  },
  {
    "date": "2026-04-14",
    "market": "Litecoin Perp Style",
    "symbol": "167LM1",
    "report": "tff",
    "open_interest": 2867,
    "change_oi": 174,
    "change_spec_net": -134,
    "spekulanter": {
      "long": 701,
      "short": 2292,
      "net": -1591,
      "label": "Hedge Funds"
    },
    "institusjoner": {
      "long": 0,
      "short": 0,
      "net": 0,
      "label": "Pensjonsfond"
    },
    "meglere": {
      "long": 0,
      "short": 0,
      "net": 0,
      "label": "Banker/Meglere"
    },
    "smahandlere": {
      "long": 382,
      "short": 149,
      "net": 233,
      "label": "Småhandlere"
    },
    "kategori": "krypto",
    "navn_no": "Litecoin Perp Style",
    "forklaring": ""
  },
  {
    "date": "2026-04-14",
    "market": "Dogecoin",
    "symbol": "168DC1",
    "report": "tff",
    "open_interest": 16448,
    "change_oi": 1120,
    "change_spec_net": -1060,
    "spekulanter": {
      "long": 973,
      "short": 16137,
      "net": -15164,
      "label": "Hedge Funds"
    },
    "institusjoner": {
      "long": 0,
      "short": 0,
      "net": 0,
      "label": "Pensjonsfond"
    },
    "meglere": {
      "long": 14805,
      "short": 0,
      "net": 14805,
      "label": "Banker/Meglere"
    },
    "smahandlere": {
      "long": 193,
      "short": 106,
      "net": 87,
      "label": "Småhandlere"
    },
    "kategori": "krypto",
    "navn_no": "Dogecoin",
    "forklaring": ""
  },
  {
    "date": "2026-04-14",
    "market": "Dogecoin Perp Style",
    "symbol": "168LM2",
    "report": "tff",
    "open_interest": 3018,
    "change_oi": 522,
    "change_spec_net": -107,
    "spekulanter": {
      "long": 1333,
      "short": 2330,
      "net": -997,
      "label": "Hedge Funds"
    },
    "institusjoner": {
      "long": 0,
      "short": 0,
      "net": 0,
      "label": "Pensjonsfond"
    },
    "meglere": {
      "long": 0,
      "short": 0,
      "net": 0,
      "label": "Banker/Meglere"
    },
    "smahandlere": {
      "long": 868,
      "short": 179,
      "net": 689,
      "label": "Småhandlere"
    },
    "kategori": "krypto",
    "navn_no": "Dogecoin Perp Style",
    "forklaring": ""
  },
  {
    "date": "2026-04-14",
    "market": "Polkadot Perp Style",
    "symbol": "169LM2",
    "report": "tff",
    "open_interest": 6544,
    "change_oi": 4177,
    "change_spec_net": -990,
    "spekulanter": {
      "long": 3790,
      "short": 6263,
      "net": -2473,
      "label": "Hedge Funds"
    },
    "institusjoner": {
      "long": 0,
      "short": 0,
      "net": 0,
      "label": "Pensjonsfond"
    },
    "meglere": {
      "long": 0,
      "short": 0,
      "net": 0,
      "label": "Banker/Meglere"
    },
    "smahandlere": {
      "long": 801,
      "short": 115,
      "net": 686,
      "label": "Småhandlere"
    },
    "kategori": "krypto",
    "navn_no": "Polkadot Perp Style",
    "forklaring": ""
  },
  {
    "date": "2026-04-14",
    "market": "Chainlink Perp Style",
    "symbol": "170LM2",
    "report": "tff",
    "open_interest": 3234,
    "change_oi": 546,
    "change_spec_net": 364,
    "spekulanter": {
      "long": 948,
      "short": 1945,
      "net": -997,
      "label": "Hedge Funds"
    },
    "institusjoner": {
      "long": 0,
      "short": 0,
      "net": 0,
      "label": "Pensjonsfond"
    },
    "meglere": {
      "long": 0,
      "short": 0,
      "net": 0,
      "label": "Banker/Meglere"
    },
    "smahandlere": {
      "long": 705,
      "short": 233,
      "net": 472,
      "label": "Småhandlere"
    },
    "kategori": "annet",
    "navn_no": "Chainlink Perp Style",
    "forklaring": ""
  },
  {
    "date": "2026-04-14",
    "market": "Avalanche",
    "symbol": "171LM1",
    "report": "tff",
    "open_interest": 1990,
    "change_oi": 35,
    "change_spec_net": 319,
    "spekulanter": {
      "long": 545,
      "short": 1451,
      "net": -906,
      "label": "Hedge Funds"
    },
    "institusjoner": {
      "long": 0,
      "short": 0,
      "net": 0,
      "label": "Pensjonsfond"
    },
    "meglere": {
      "long": 0,
      "short": 0,
      "net": 0,
      "label": "Banker/Meglere"
    },
    "smahandlere": {
      "long": 173,
      "short": 72,
      "net": 101,
      "label": "Småhandlere"
    },
    "kategori": "annet",
    "navn_no": "Avalanche",
    "forklaring": ""
  },
  {
    "date": "2026-04-14",
    "market": "Avalanche Perp Style",
    "symbol": "171LM2",
    "report": "tff",
    "open_interest": 3855,
    "change_oi": -213,
    "change_spec_net": 61,
    "spekulanter": {
      "long": 0,
      "short": 2129,
      "net": -2129,
      "label": "Hedge Funds"
    },
    "institusjoner": {
      "long": 0,
      "short": 0,
      "net": 0,
      "label": "Pensjonsfond"
    },
    "meglere": {
      "long": 0,
      "short": 0,
      "net": 0,
      "label": "Banker/Meglere"
    },
    "smahandlere": {
      "long": 755,
      "short": 145,
      "net": 610,
      "label": "Småhandlere"
    },
    "kategori": "annet",
    "navn_no": "Avalanche Perp Style",
    "forklaring": ""
  },
  {
    "date": "2026-04-14",
    "market": "1K Shib Perp",
    "symbol": "172LM2",
    "report": "tff",
    "open_interest": 2220,
    "change_oi": 484,
    "change_spec_net": -191,
    "spekulanter": {
      "long": 727,
      "short": 1895,
      "net": -1168,
      "label": "Hedge Funds"
    },
    "institusjoner": {
      "long": 0,
      "short": 0,
      "net": 0,
      "label": "Pensjonsfond"
    },
    "meglere": {
      "long": 0,
      "short": 0,
      "net": 0,
      "label": "Banker/Meglere"
    },
    "smahandlere": {
      "long": 528,
      "short": 51,
      "net": 477,
      "label": "Småhandlere"
    },
    "kategori": "annet",
    "navn_no": "1K Shib Perp",
    "forklaring": ""
  },
  {
    "date": "2026-01-20",
    "market": "Cardona",
    "symbol": "174LM1",
    "report": "tff",
    "open_interest": 1159,
    "change_oi": -237,
    "change_spec_net": -292,
    "spekulanter": {
      "long": 0,
      "short": 865,
      "net": -865,
      "label": "Hedge Funds"
    },
    "institusjoner": {
      "long": 0,
      "short": 0,
      "net": 0,
      "label": "Pensjonsfond"
    },
    "meglere": {
      "long": 0,
      "short": 0,
      "net": 0,
      "label": "Banker/Meglere"
    },
    "smahandlere": {
      "long": 255,
      "short": 72,
      "net": 183,
      "label": "Småhandlere"
    },
    "kategori": "annet",
    "navn_no": "Cardona",
    "forklaring": ""
  },
  {
    "date": "2026-04-14",
    "market": "Cardona Perp Style",
    "symbol": "174LM2",
    "report": "tff",
    "open_interest": 5396,
    "change_oi": 1038,
    "change_spec_net": -442,
    "spekulanter": {
      "long": 775,
      "short": 4079,
      "net": -3304,
      "label": "Hedge Funds"
    },
    "institusjoner": {
      "long": 0,
      "short": 0,
      "net": 0,
      "label": "Pensjonsfond"
    },
    "meglere": {
      "long": 0,
      "short": 0,
      "net": 0,
      "label": "Banker/Meglere"
    },
    "smahandlere": {
      "long": 1178,
      "short": 216,
      "net": 962,
      "label": "Småhandlere"
    },
    "kategori": "annet",
    "navn_no": "Cardona Perp Style",
    "forklaring": ""
  },
  {
    "date": "2026-04-14",
    "market": "Nano Xrp",
    "symbol": "176LM1",
    "report": "tff",
    "open_interest": 23585,
    "change_oi": 9057,
    "change_spec_net": -1766,
    "spekulanter": {
      "long": 20168,
      "short": 22605,
      "net": -2437,
      "label": "Hedge Funds"
    },
    "institusjoner": {
      "long": 0,
      "short": 0,
      "net": 0,
      "label": "Pensjonsfond"
    },
    "meglere": {
      "long": 0,
      "short": 0,
      "net": 0,
      "label": "Banker/Meglere"
    },
    "smahandlere": {
      "long": 598,
      "short": 235,
      "net": 363,
      "label": "Småhandlere"
    },
    "kategori": "krypto",
    "navn_no": "XRP Mini",
    "forklaring": "XRP – brukes til internasjonal betaling."
  },
  {
    "date": "2026-04-14",
    "market": "Nano Xrp Perp Style",
    "symbol": "176LM3",
    "report": "tff",
    "open_interest": 20753,
    "change_oi": 3444,
    "change_spec_net": 39,
    "spekulanter": {
      "long": 3894,
      "short": 16750,
      "net": -12856,
      "label": "Hedge Funds"
    },
    "institusjoner": {
      "long": 0,
      "short": 0,
      "net": 0,
      "label": "Pensjonsfond"
    },
    "meglere": {
      "long": 0,
      "short": 48,
      "net": -48,
      "label": "Banker/Meglere"
    },
    "smahandlere": {
      "long": 4267,
      "short": 549,
      "net": 3718,
      "label": "Småhandlere"
    },
    "kategori": "krypto",
    "navn_no": "Nano Xrp Perp Style",
    "forklaring": ""
  },
  {
    "date": "2026-02-24",
    "market": "Micro Sol",
    "symbol": "177742",
    "report": "tff",
    "open_interest": 3558,
    "change_oi": 420,
    "change_spec_net": -303,
    "spekulanter": {
      "long": 884,
      "short": 2944,
      "net": -2060,
      "label": "Hedge Funds"
    },
    "institusjoner": {
      "long": 30,
      "short": 0,
      "net": 30,
      "label": "Pensjonsfond"
    },
    "meglere": {
      "long": 1283,
      "short": 100,
      "net": 1183,
      "label": "Banker/Meglere"
    },
    "smahandlere": {
      "long": 776,
      "short": 363,
      "net": 413,
      "label": "Småhandlere"
    },
    "kategori": "annet",
    "navn_no": "Micro Sol",
    "forklaring": ""
  },
  {
    "date": "2026-04-14",
    "market": "Nano Solana",
    "symbol": "177LM1",
    "report": "tff",
    "open_interest": 10700,
    "change_oi": 2800,
    "change_spec_net": 500,
    "spekulanter": {
      "long": 7056,
      "short": 8734,
      "net": -1678,
      "label": "Hedge Funds"
    },
    "institusjoner": {
      "long": 0,
      "short": 0,
      "net": 0,
      "label": "Pensjonsfond"
    },
    "meglere": {
      "long": 0,
      "short": 0,
      "net": 0,
      "label": "Banker/Meglere"
    },
    "smahandlere": {
      "long": 545,
      "short": 386,
      "net": 159,
      "label": "Småhandlere"
    },
    "kategori": "krypto",
    "navn_no": "Solana Mini",
    "forklaring": "Solana – rask og billig blokkjede."
  },
  {
    "date": "2026-04-14",
    "market": "Nano Solana Perp Style",
    "symbol": "177LM3",
    "report": "tff",
    "open_interest": 35033,
    "change_oi": 1734,
    "change_spec_net": 3665,
    "spekulanter": {
      "long": 1447,
      "short": 19837,
      "net": -18390,
      "label": "Hedge Funds"
    },
    "institusjoner": {
      "long": 0,
      "short": 0,
      "net": 0,
      "label": "Pensjonsfond"
    },
    "meglere": {
      "long": 0,
      "short": 74,
      "net": -74,
      "label": "Banker/Meglere"
    },
    "smahandlere": {
      "long": 9955,
      "short": 6209,
      "net": 3746,
      "label": "Småhandlere"
    },
    "kategori": "krypto",
    "navn_no": "Solana Mini Perp",
    "forklaring": "Solana uten utløpsdato."
  },
  {
    "date": "2026-04-14",
    "market": "Sui Perp Style",
    "symbol": "180LM3",
    "report": "tff",
    "open_interest": 1586,
    "change_oi": -1771,
    "change_spec_net": 32,
    "spekulanter": {
      "long": 55,
      "short": 854,
      "net": -799,
      "label": "Hedge Funds"
    },
    "institusjoner": {
      "long": 0,
      "short": 0,
      "net": 0,
      "label": "Pensjonsfond"
    },
    "meglere": {
      "long": 0,
      "short": 0,
      "net": 0,
      "label": "Banker/Meglere"
    },
    "smahandlere": {
      "long": 576,
      "short": 275,
      "net": 301,
      "label": "Småhandlere"
    },
    "kategori": "krypto",
    "navn_no": "Sui Perp Style",
    "forklaring": ""
  },
  {
    "date": "2026-04-14",
    "market": "Hedera Perp Style",
    "symbol": "180LM4",
    "report": "tff",
    "open_interest": 1302,
    "change_oi": 266,
    "change_spec_net": -263,
    "spekulanter": {
      "long": 28,
      "short": 811,
      "net": -783,
      "label": "Hedge Funds"
    },
    "institusjoner": {
      "long": 0,
      "short": 0,
      "net": 0,
      "label": "Pensjonsfond"
    },
    "meglere": {
      "long": 0,
      "short": 0,
      "net": 0,
      "label": "Banker/Meglere"
    },
    "smahandlere": {
      "long": 611,
      "short": 144,
      "net": 467,
      "label": "Småhandlere"
    },
    "kategori": "annet",
    "navn_no": "Hedera Perp Style",
    "forklaring": ""
  },
  {
    "date": "2026-04-14",
    "market": "Ondo Perp Style",
    "symbol": "180LM8",
    "report": "tff",
    "open_interest": 1333,
    "change_oi": 0,
    "change_spec_net": 0,
    "spekulanter": {
      "long": 38,
      "short": 1178,
      "net": -1140,
      "label": "Hedge Funds"
    },
    "institusjoner": {
      "long": 0,
      "short": 0,
      "net": 0,
      "label": "Pensjonsfond"
    },
    "meglere": {
      "long": 0,
      "short": 0,
      "net": 0,
      "label": "Banker/Meglere"
    },
    "smahandlere": {
      "long": 251,
      "short": 91,
      "net": 160,
      "label": "Småhandlere"
    },
    "kategori": "annet",
    "navn_no": "Ondo Perp Style",
    "forklaring": ""
  },
  {
    "date": "2026-04-14",
    "market": "Zcash Perp Style",
    "symbol": "180LMB",
    "report": "tff",
    "open_interest": 2551,
    "change_oi": 983,
    "change_spec_net": 1,
    "spekulanter": {
      "long": 0,
      "short": 374,
      "net": -374,
      "label": "Hedge Funds"
    },
    "institusjoner": {
      "long": 0,
      "short": 0,
      "net": 0,
      "label": "Pensjonsfond"
    },
    "meglere": {
      "long": 0,
      "short": 0,
      "net": 0,
      "label": "Banker/Meglere"
    },
    "smahandlere": {
      "long": 639,
      "short": 504,
      "net": 135,
      "label": "Småhandlere"
    },
    "kategori": "krypto",
    "navn_no": "Zcash Perp Style",
    "forklaring": ""
  },
  {
    "date": "2026-04-14",
    "market": "Bitcoin",
    "symbol": "133741",
    "report": "tff",
    "open_interest": 23761,
    "change_oi": 1453,
    "change_spec_net": -1812,
    "spekulanter": {
      "long": 3318,
      "short": 13557,
      "net": -10239,
      "label": "Hedge Funds"
    },
    "institusjoner": {
      "long": 6505,
      "short": 1244,
      "net": 5261,
      "label": "Pensjonsfond"
    },
    "meglere": {
      "long": 6520,
      "short": 2326,
      "net": 4194,
      "label": "Banker/Meglere"
    },
    "smahandlere": {
      "long": 1012,
      "short": 1162,
      "net": -150,
      "label": "Småhandlere"
    },
    "kategori": "krypto",
    "navn_no": "Bitcoin (BTC)",
    "forklaring": "Verdens største kryptovaluta."
  },
  {
    "date": "2026-04-14",
    "market": "Ether Cash Settled",
    "symbol": "146021",
    "report": "tff",
    "open_interest": 34354,
    "change_oi": 5706,
    "change_spec_net": -1922,
    "spekulanter": {
      "long": 2080,
      "short": 14029,
      "net": -11949,
      "label": "Hedge Funds"
    },
    "institusjoner": {
      "long": 2976,
      "short": 2449,
      "net": 527,
      "label": "Pensjonsfond"
    },
    "meglere": {
      "long": 18421,
      "short": 7569,
      "net": 10852,
      "label": "Banker/Meglere"
    },
    "smahandlere": {
      "long": 824,
      "short": 519,
      "net": 305,
      "label": "Småhandlere"
    },
    "kategori": "krypto",
    "navn_no": "Ether Cash Settled",
    "forklaring": ""
  },
  {
    "date": "2026-04-14",
    "market": "Xrp",
    "symbol": "176740",
    "report": "tff",
    "open_interest": 7554,
    "change_oi": 155,
    "change_spec_net": -146,
    "spekulanter": {
      "long": 286,
      "short": 3660,
      "net": -3374,
      "label": "Hedge Funds"
    },
    "institusjoner": {
      "long": 802,
      "short": 863,
      "net": -61,
      "label": "Pensjonsfond"
    },
    "meglere": {
      "long": 5201,
      "short": 1292,
      "net": 3909,
      "label": "Banker/Meglere"
    },
    "smahandlere": {
      "long": 75,
      "short": 392,
      "net": -317,
      "label": "Småhandlere"
    },
    "kategori": "krypto",
    "navn_no": "XRP",
    "forklaring": "XRP kryptovaluta."
  },
  {
    "date": "2026-04-14",
    "market": "Sol",
    "symbol": "177741",
    "report": "tff",
    "open_interest": 14310,
    "change_oi": -24,
    "change_spec_net": 120,
    "spekulanter": {
      "long": 901,
      "short": 4699,
      "net": -3798,
      "label": "Hedge Funds"
    },
    "institusjoner": {
      "long": 732,
      "short": 1789,
      "net": -1057,
      "label": "Pensjonsfond"
    },
    "meglere": {
      "long": 9271,
      "short": 4345,
      "net": 4926,
      "label": "Banker/Meglere"
    },
    "smahandlere": {
      "long": 324,
      "short": 420,
      "net": -96,
      "label": "Småhandlere"
    },
    "kategori": "annet",
    "navn_no": "Solana (SOL)",
    "forklaring": "Solana kryptovaluta."
  },
  {
    "date": "2026-04-14",
    "market": "Usd Index",
    "symbol": "098662",
    "report": "tff",
    "open_interest": 32911,
    "change_oi": -3662,
    "change_spec_net": 5546,
    "spekulanter": {
      "long": 10581,
      "short": 13676,
      "net": -3095,
      "label": "Hedge Funds"
    },
    "institusjoner": {
      "long": 10151,
      "short": 1613,
      "net": 8538,
      "label": "Pensjonsfond"
    },
    "meglere": {
      "long": 3301,
      "short": 10473,
      "net": -7172,
      "label": "Banker/Meglere"
    },
    "smahandlere": {
      "long": 2580,
      "short": 2345,
      "net": 235,
      "label": "Småhandlere"
    },
    "kategori": "valuta",
    "navn_no": "Dollarindeks (DXY)",
    "forklaring": "Styrken til USD mot 6 valutaer."
  },
  {
    "date": "2026-04-14",
    "market": "Vix Futures",
    "symbol": "1170E1",
    "report": "tff",
    "open_interest": 365168,
    "change_oi": 18563,
    "change_spec_net": 15137,
    "spekulanter": {
      "long": 65256,
      "short": 95078,
      "net": -29822,
      "label": "Hedge Funds"
    },
    "institusjoner": {
      "long": 48923,
      "short": 47654,
      "net": 1269,
      "label": "Pensjonsfond"
    },
    "meglere": {
      "long": 77943,
      "short": 51710,
      "net": 26233,
      "label": "Banker/Meglere"
    },
    "smahandlere": {
      "long": 25830,
      "short": 24548,
      "net": 1282,
      "label": "Småhandlere"
    },
    "kategori": "aksjer",
    "navn_no": "VIX – Fryktindeks",
    "forklaring": "Høy verdi = mye usikkerhet i markedet."
  }
]