[
  {
    "date": "2021-12-28",
    "market": "Canadian Dollar",
    "symbol": "090741",
    "report": "tff",
    "open_interest": 138692,
    "change_oi": -6870,
    "change_spec_net": 188,
    "spekulanter": {
      "long": 12466,
      "short": 39885,
      "net": -27419,
      "label": "Hedge Funds"
    },
    "institusjoner": {
      "long": 39561,
      "short": 42085,
      "net": -2524,
      "label": "Pensjonsfond"
    },
    "meglere": {
      "long": 33018,
      "short": 15462,
      "net": 17556,
      "label": "Banker/Meglere"
    },
    "smahandlere": {
      "long": 29912,
      "short": 26745,
      "net": 3167,
      "label": "Småhandlere"
    },
    "kategori": "valuta",
    "navn_no": "Kanadisk Dollar",
    "forklaring": "Tett knyttet til oljeprisen."
  },
  {
    "date": "2021-12-28",
    "market": "Swiss Franc",
    "symbol": "092741",
    "report": "tff",
    "open_interest": 40122,
    "change_oi": -798,
    "change_spec_net": -2384,
    "spekulanter": {
      "long": 2260,
      "short": 5744,
      "net": -3484,
      "label": "Hedge Funds"
    },
    "institusjoner": {
      "long": 4859,
      "short": 13857,
      "net": -8998,
      "label": "Pensjonsfond"
    },
    "meglere": {
      "long": 18957,
      "short": 1481,
      "net": 17476,
      "label": "Banker/Meglere"
    },
    "smahandlere": {
      "long": 12618,
      "short": 17126,
      "net": -4508,
      "label": "Småhandlere"
    },
    "kategori": "valuta",
    "navn_no": "Sveitsisk Franc",
    "forklaring": "En av de sikreste valutaene i verden."
  },
  {
    "date": "2021-12-28",
    "market": "British Pound Sterling",
    "symbol": "096742",
    "report": "tff",
    "open_interest": 205378,
    "change_oi": -2369,
    "change_spec_net": -3228,
    "spekulanter": {
      "long": 25821,
      "short": 39881,
      "net": -14060,
      "label": "Hedge Funds"
    },
    "institusjoner": {
      "long": 33119,
      "short": 93269,
      "net": -60150,
      "label": "Pensjonsfond"
    },
    "meglere": {
      "long": 109263,
      "short": 20658,
      "net": 88605,
      "label": "Banker/Meglere"
    },
    "smahandlere": {
      "long": 22191,
      "short": 31573,
      "net": -9382,
      "label": "Småhandlere"
    },
    "kategori": "valuta",
    "navn_no": "British Pound Sterling",
    "forklaring": ""
  },
  {
    "date": "2021-12-28",
    "market": "Japanese Yen",
    "symbol": "097741",
    "report": "tff",
    "open_interest": 203814,
    "change_oi": 20071,
    "change_spec_net": -169,
    "spekulanter": {
      "long": 33153,
      "short": 54022,
      "net": -20869,
      "label": "Hedge Funds"
    },
    "institusjoner": {
      "long": 40821,
      "short": 98235,
      "net": -57414,
      "label": "Pensjonsfond"
    },
    "meglere": {
      "long": 102130,
      "short": 4107,
      "net": 98023,
      "label": "Banker/Meglere"
    },
    "smahandlere": {
      "long": 16525,
      "short": 35787,
      "net": -19262,
      "label": "Småhandlere"
    },
    "kategori": "valuta",
    "navn_no": "Japansk Yen",
    "forklaring": "Trygg-havn-valuta i urolige tider."
  },
  {
    "date": "2021-12-28",
    "market": "Euro Fx",
    "symbol": "099741",
    "report": "tff",
    "open_interest": 673273,
    "change_oi": 1034,
    "change_spec_net": 1271,
    "spekulanter": {
      "long": 57637,
      "short": 108038,
      "net": -50401,
      "label": "Hedge Funds"
    },
    "institusjoner": {
      "long": 403923,
      "short": 167507,
      "net": 236416,
      "label": "Pensjonsfond"
    },
    "meglere": {
      "long": 31727,
      "short": 281161,
      "net": -249434,
      "label": "Banker/Meglere"
    },
    "smahandlere": {
      "long": 76739,
      "short": 51572,
      "net": 25167,
      "label": "Småhandlere"
    },
    "kategori": "valuta",
    "navn_no": "Euro (EUR/USD)",
    "forklaring": "Verdens mest handlede valutapar."
  },
  {
    "date": "2021-12-28",
    "market": "Australian Dollar",
    "symbol": "232741",
    "report": "tff",
    "open_interest": 183152,
    "change_oi": -8157,
    "change_spec_net": -4000,
    "spekulanter": {
      "long": 14666,
      "short": 35231,
      "net": -20565,
      "label": "Hedge Funds"
    },
    "institusjoner": {
      "long": 26867,
      "short": 101924,
      "net": -75057,
      "label": "Pensjonsfond"
    },
    "meglere": {
      "long": 117177,
      "short": 4735,
      "net": 112442,
      "label": "Banker/Meglere"
    },
    "smahandlere": {
      "long": 16785,
      "short": 34520,
      "net": -17735,
      "label": "Småhandlere"
    },
    "kategori": "valuta",
    "navn_no": "Australsk Dollar",
    "forklaring": "Råvarevaluta – følger kobber og jernmalm."
  },
  {
    "date": "2021-12-28",
    "market": "Euro Fx/British Pound Xrate",
    "symbol": "299741",
    "report": "tff",
    "open_interest": 32372,
    "change_oi": 420,
    "change_spec_net": 435,
    "spekulanter": {
      "long": 432,
      "short": 3740,
      "net": -3308,
      "label": "Hedge Funds"
    },
    "institusjoner": {
      "long": 14685,
      "short": 7421,
      "net": 7264,
      "label": "Pensjonsfond"
    },
    "meglere": {
      "long": 1349,
      "short": 12364,
      "net": -11015,
      "label": "Banker/Meglere"
    },
    "smahandlere": {
      "long": 13249,
      "short": 6190,
      "net": 7059,
      "label": "Småhandlere"
    },
    "kategori": "valuta",
    "navn_no": "Euro Fx/British Pound Xrate",
    "forklaring": ""
  },
  {
    "date": "2021-12-28",
    "market": "Euro Fx/Japanese Yen Xrate",
    "symbol": "399741",
    "report": "tff",
    "open_interest": 26698,
    "change_oi": -71,
    "change_spec_net": -75,
    "spekulanter": {
      "long": 2269,
      "short": 1545,
      "net": 724,
      "label": "Hedge Funds"
    },
    "institusjoner": {
      "long": 5017,
      "short": 17724,
      "net": -12707,
      "label": "Pensjonsfond"
    },
    "meglere": {
      "long": 9838,
      "short": 0,
      "net": 9838,
      "label": "Banker/Meglere"
    },
    "smahandlere": {
      "long": 7741,
      "short": 5596,
      "net": 2145,
      "label": "Småhandlere"
    },
    "kategori": "valuta",
    "navn_no": "Euro Fx/Japanese Yen Xrate",
    "forklaring": ""
  },
  {
    "date": "2021-12-28",
    "market": "Russian Ruble",
    "symbol": "089741",
    "report": "tff",
    "open_interest": 47726,
    "change_oi": 2354,
    "change_spec_net": -708,
    "spekulanter": {
      "long": 8061,
      "short": 6561,
      "net": 1500,
      "label": "Hedge Funds"
    },
    "institusjoner": {
      "long": 34415,
      "short": 0,
      "net": 34415,
      "label": "Pensjonsfond"
    },
    "meglere": {
      "long": 143,
      "short": 33318,
      "net": -33175,
      "label": "Banker/Meglere"
    },
    "smahandlere": {
      "long": 2228,
      "short": 806,
      "net": 1422,
      "label": "Småhandlere"
    },
    "kategori": "annet",
    "navn_no": "Russian Ruble",
    "forklaring": ""
  },
  {
    "date": "2021-12-28",
    "market": "Mexican Peso",
    "symbol": "095741",
    "report": "tff",
    "open_interest": 102418,
    "change_oi": 7949,
    "change_spec_net": -7632,
    "spekulanter": {
      "long": 31625,
      "short": 42878,
      "net": -11253,
      "label": "Hedge Funds"
    },
    "institusjoner": {
      "long": 58075,
      "short": 7847,
      "net": 50228,
      "label": "Pensjonsfond"
    },
    "meglere": {
      "long": 1222,
      "short": 23948,
      "net": -22726,
      "label": "Banker/Meglere"
    },
    "smahandlere": {
      "long": 4815,
      "short": 4141,
      "net": 674,
      "label": "Småhandlere"
    },
    "kategori": "valuta",
    "navn_no": "Mexican Peso",
    "forklaring": ""
  },
  {
    "date": "2021-12-28",
    "market": "Brazilian Real",
    "symbol": "102741",
    "report": "tff",
    "open_interest": 37384,
    "change_oi": 6573,
    "change_spec_net": -1756,
    "spekulanter": {
      "long": 9370,
      "short": 19244,
      "net": -9874,
      "label": "Hedge Funds"
    },
    "institusjoner": {
      "long": 4263,
      "short": 2511,
      "net": 1752,
      "label": "Pensjonsfond"
    },
    "meglere": {
      "long": 9093,
      "short": 3260,
      "net": 5833,
      "label": "Banker/Meglere"
    },
    "smahandlere": {
      "long": 2542,
      "short": 2749,
      "net": -207,
      "label": "Småhandlere"
    },
    "kategori": "valuta",
    "navn_no": "Brazilian Real",
    "forklaring": ""
  },
  {
    "date": "2021-12-28",
    "market": "New Zealand Dollar",
    "symbol": "112741",
    "report": "tff",
    "open_interest": 41862,
    "change_oi": 508,
    "change_spec_net": -1392,
    "spekulanter": {
      "long": 11833,
      "short": 12186,
      "net": -353,
      "label": "Hedge Funds"
    },
    "institusjoner": {
      "long": 4010,
      "short": 20108,
      "net": -16098,
      "label": "Pensjonsfond"
    },
    "meglere": {
      "long": 21075,
      "short": 1719,
      "net": 19356,
      "label": "Banker/Meglere"
    },
    "smahandlere": {
      "long": 3025,
      "short": 4704,
      "net": -1679,
      "label": "Småhandlere"
    },
    "kategori": "annet",
    "navn_no": "New Zealand Dollar",
    "forklaring": ""
  },
  {
    "date": "2021-12-28",
    "market": "South African Rand",
    "symbol": "122741",
    "report": "tff",
    "open_interest": 10553,
    "change_oi": -50,
    "change_spec_net": -1803,
    "spekulanter": {
      "long": 1378,
      "short": 5169,
      "net": -3791,
      "label": "Hedge Funds"
    },
    "institusjoner": {
      "long": 3430,
      "short": 2595,
      "net": 835,
      "label": "Pensjonsfond"
    },
    "meglere": {
      "long": 3927,
      "short": 0,
      "net": 3927,
      "label": "Banker/Meglere"
    },
    "smahandlere": {
      "long": 799,
      "short": 1786,
      "net": -987,
      "label": "Småhandlere"
    },
    "kategori": "annet",
    "navn_no": "South African Rand",
    "forklaring": ""
  },
  {
    "date": "2021-12-28",
    "market": "Djia Consolidated",
    "symbol": "12460+",
    "report": "tff",
    "open_interest": 48375,
    "change_oi": 2683,
    "change_spec_net": 69,
    "spekulanter": {
      "long": 12840,
      "short": 6147,
      "net": 6693,
      "label": "Hedge Funds"
    },
    "institusjoner": {
      "long": 11772,
      "short": 1268,
      "net": 10504,
      "label": "Pensjonsfond"
    },
    "meglere": {
      "long": 15404,
      "short": 18636,
      "net": -3232,
      "label": "Banker/Meglere"
    },
    "smahandlere": {
      "long": 7311,
      "short": 5767,
      "net": 1544,
      "label": "Småhandlere"
    },
    "kategori": "annet",
    "navn_no": "Djia Consolidated",
    "forklaring": ""
  },
  {
    "date": "2021-12-28",
    "market": "Dow Jones Industrial Avg",
    "symbol": "124603",
    "report": "tff",
    "open_interest": 96749,
    "change_oi": 5365,
    "change_spec_net": 137,
    "spekulanter": {
      "long": 25679,
      "short": 12293,
      "net": 13386,
      "label": "Hedge Funds"
    },
    "institusjoner": {
      "long": 23543,
      "short": 2535,
      "net": 21008,
      "label": "Pensjonsfond"
    },
    "meglere": {
      "long": 30808,
      "short": 37272,
      "net": -6464,
      "label": "Banker/Meglere"
    },
    "smahandlere": {
      "long": 14621,
      "short": 11534,
      "net": 3087,
      "label": "Småhandlere"
    },
    "kategori": "aksjer",
    "navn_no": "Dow Jones Industrial Avg",
    "forklaring": ""
  },
  {
    "date": "2021-12-28",
    "market": "Dow Jones U.S. Real Estate Idx",
    "symbol": "124606",
    "report": "tff",
    "open_interest": 43354,
    "change_oi": 4216,
    "change_spec_net": -670,
    "spekulanter": {
      "long": 1722,
      "short": 4388,
      "net": -2666,
      "label": "Hedge Funds"
    },
    "institusjoner": {
      "long": 25739,
      "short": 9247,
      "net": 16492,
      "label": "Pensjonsfond"
    },
    "meglere": {
      "long": 11747,
      "short": 27168,
      "net": -15421,
      "label": "Banker/Meglere"
    },
    "smahandlere": {
      "long": 2325,
      "short": 730,
      "net": 1595,
      "label": "Småhandlere"
    },
    "kategori": "aksjer",
    "navn_no": "Dow Jones U.S. Real Estate Idx",
    "forklaring": ""
  },
  {
    "date": "2021-12-28",
    "market": "S&P 500 Consolidated",
    "symbol": "13874+",
    "report": "tff",
    "open_interest": 457570,
    "change_oi": 5146,
    "change_spec_net": -17361,
    "spekulanter": {
      "long": 51013,
      "short": 70467,
      "net": -19454,
      "label": "Hedge Funds"
    },
    "institusjoner": {
      "long": 223273,
      "short": 76055,
      "net": 147218,
      "label": "Pensjonsfond"
    },
    "meglere": {
      "long": 32744,
      "short": 123660,
      "net": -90916,
      "label": "Banker/Meglere"
    },
    "smahandlere": {
      "long": 51933,
      "short": 45036,
      "net": 6897,
      "label": "Småhandlere"
    },
    "kategori": "aksjer",
    "navn_no": "S&P 500",
    "forklaring": "De 500 største selskapene i USA."
  },
  {
    "date": "2021-09-14",
    "market": "S&P 500 Stock Index",
    "symbol": "138741",
    "report": "tff",
    "open_interest": 45572,
    "change_oi": -69,
    "change_spec_net": 4299,
    "spekulanter": {
      "long": 22721,
      "short": 14632,
      "net": 8089,
      "label": "Hedge Funds"
    },
    "institusjoner": {
      "long": 1000,
      "short": 0,
      "net": 1000,
      "label": "Pensjonsfond"
    },
    "meglere": {
      "long": 18300,
      "short": 4725,
      "net": 13575,
      "label": "Banker/Meglere"
    },
    "smahandlere": {
      "long": 3151,
      "short": 25915,
      "net": -22764,
      "label": "Småhandlere"
    },
    "kategori": "aksjer",
    "navn_no": "S&P 500 Stock Index",
    "forklaring": ""
  },
  {
    "date": "2021-12-28",
    "market": "E",
    "symbol": "138749",
    "report": "tff",
    "open_interest": 26837,
    "change_oi": -979,
    "change_spec_net": -385,
    "spekulanter": {
      "long": 3248,
      "short": 1533,
      "net": 1715,
      "label": "Hedge Funds"
    },
    "institusjoner": {
      "long": 9568,
      "short": 3761,
      "net": 5807,
      "label": "Pensjonsfond"
    },
    "meglere": {
      "long": 10388,
      "short": 20963,
      "net": -10575,
      "label": "Banker/Meglere"
    },
    "smahandlere": {
      "long": 3633,
      "short": 580,
      "net": 3053,
      "label": "Småhandlere"
    },
    "kategori": "aksjer",
    "navn_no": "E",
    "forklaring": ""
  },
  {
    "date": "2021-03-16",
    "market": "S&P 500 Total Return Index",
    "symbol": "13874N",
    "report": "tff",
    "open_interest": 139760,
    "change_oi": 13822,
    "change_spec_net": 0,
    "spekulanter": {
      "long": 7607,
      "short": 0,
      "net": 7607,
      "label": "Hedge Funds"
    },
    "institusjoner": {
      "long": 0,
      "short": 0,
      "net": 0,
      "label": "Pensjonsfond"
    },
    "meglere": {
      "long": 92357,
      "short": 99464,
      "net": -7107,
      "label": "Banker/Meglere"
    },
    "smahandlere": {
      "long": 0,
      "short": 500,
      "net": -500,
      "label": "Småhandlere"
    },
    "kategori": "aksjer",
    "navn_no": "S&P 500 Total Return Index",
    "forklaring": ""
  },
  {
    "date": "2021-12-28",
    "market": "Micro E",
    "symbol": "209747",
    "report": "tff",
    "open_interest": 59282,
    "change_oi": 855,
    "change_spec_net": 12073,
    "spekulanter": {
      "long": 21576,
      "short": 32546,
      "net": -10970,
      "label": "Hedge Funds"
    },
    "institusjoner": {
      "long": 904,
      "short": 0,
      "net": 904,
      "label": "Pensjonsfond"
    },
    "meglere": {
      "long": 994,
      "short": 547,
      "net": 447,
      "label": "Banker/Meglere"
    },
    "smahandlere": {
      "long": 30849,
      "short": 22411,
      "net": 8438,
      "label": "Småhandlere"
    },
    "kategori": "aksjer",
    "navn_no": "Micro E",
    "forklaring": ""
  },
  {
    "date": "2021-12-28",
    "market": "Nasdaq",
    "symbol": "20974+",
    "report": "tff",
    "open_interest": 42219,
    "change_oi": 605,
    "change_spec_net": -1859,
    "spekulanter": {
      "long": 6556,
      "short": 9776,
      "net": -3220,
      "label": "Hedge Funds"
    },
    "institusjoner": {
      "long": 14985,
      "short": 7534,
      "net": 7451,
      "label": "Pensjonsfond"
    },
    "meglere": {
      "long": 10499,
      "short": 13956,
      "net": -3457,
      "label": "Banker/Meglere"
    },
    "smahandlere": {
      "long": 7090,
      "short": 6903,
      "net": 187,
      "label": "Småhandlere"
    },
    "kategori": "aksjer",
    "navn_no": "Nasdaq 100",
    "forklaring": "Teknologiindeks. Apple, Microsoft, Nvidia m.fl."
  },
  {
    "date": "2021-12-28",
    "market": "Emini Russell 1000 Value Index",
    "symbol": "239744",
    "report": "tff",
    "open_interest": 22670,
    "change_oi": 575,
    "change_spec_net": -1,
    "spekulanter": {
      "long": 1440,
      "short": 795,
      "net": 645,
      "label": "Hedge Funds"
    },
    "institusjoner": {
      "long": 13137,
      "short": 497,
      "net": 12640,
      "label": "Pensjonsfond"
    },
    "meglere": {
      "long": 6959,
      "short": 21187,
      "net": -14228,
      "label": "Banker/Meglere"
    },
    "smahandlere": {
      "long": 1134,
      "short": 191,
      "net": 943,
      "label": "Småhandlere"
    },
    "kategori": "aksjer",
    "navn_no": "Emini Russell 1000 Value Index",
    "forklaring": ""
  },
  {
    "date": "2021-12-28",
    "market": "Nikkei Stock Average",
    "symbol": "240741",
    "report": "tff",
    "open_interest": 15319,
    "change_oi": -14,
    "change_spec_net": -364,
    "spekulanter": {
      "long": 230,
      "short": 6678,
      "net": -6448,
      "label": "Hedge Funds"
    },
    "institusjoner": {
      "long": 10392,
      "short": 0,
      "net": 10392,
      "label": "Pensjonsfond"
    },
    "meglere": {
      "long": 0,
      "short": 3185,
      "net": -3185,
      "label": "Banker/Meglere"
    },
    "smahandlere": {
      "long": 3969,
      "short": 3035,
      "net": 934,
      "label": "Småhandlere"
    },
    "kategori": "aksjer",
    "navn_no": "Nikkei (Japan)",
    "forklaring": "225 største selskaper på Tokyo-børsen."
  },
  {
    "date": "2021-12-28",
    "market": "Nikkei Stock Average Yen Denom",
    "symbol": "240743",
    "report": "tff",
    "open_interest": 41696,
    "change_oi": -704,
    "change_spec_net": -853,
    "spekulanter": {
      "long": 10618,
      "short": 9932,
      "net": 686,
      "label": "Hedge Funds"
    },
    "institusjoner": {
      "long": 12587,
      "short": 4098,
      "net": 8489,
      "label": "Pensjonsfond"
    },
    "meglere": {
      "long": 4214,
      "short": 2875,
      "net": 1339,
      "label": "Banker/Meglere"
    },
    "smahandlere": {
      "long": 6485,
      "short": 23223,
      "net": -16738,
      "label": "Småhandlere"
    },
    "kategori": "aksjer",
    "navn_no": "Nikkei Stock Average Yen Denom",
    "forklaring": ""
  },
  {
    "date": "2021-12-28",
    "market": "Msci Eafe Mini Index",
    "symbol": "244041",
    "report": "tff",
    "open_interest": 386104,
    "change_oi": -43,
    "change_spec_net": -11468,
    "spekulanter": {
      "long": 18284,
      "short": 19212,
      "net": -928,
      "label": "Hedge Funds"
    },
    "institusjoner": {
      "long": 271940,
      "short": 77459,
      "net": 194481,
      "label": "Pensjonsfond"
    },
    "meglere": {
      "long": 32288,
      "short": 215612,
      "net": -183324,
      "label": "Banker/Meglere"
    },
    "smahandlere": {
      "long": 11330,
      "short": 6618,
      "net": 4712,
      "label": "Småhandlere"
    },
    "kategori": "aksjer",
    "navn_no": "Msci Eafe Mini Index",
    "forklaring": ""
  },
  {
    "date": "2021-12-28",
    "market": "Msci Emerging Mkts Index",
    "symbol": "244042",
    "report": "tff",
    "open_interest": 1077807,
    "change_oi": -6345,
    "change_spec_net": -22922,
    "spekulanter": {
      "long": 73221,
      "short": 67138,
      "net": 6083,
      "label": "Hedge Funds"
    },
    "institusjoner": {
      "long": 683368,
      "short": 339271,
      "net": 344097,
      "label": "Pensjonsfond"
    },
    "meglere": {
      "long": 109243,
      "short": 490445,
      "net": -381202,
      "label": "Banker/Meglere"
    },
    "smahandlere": {
      "long": 24623,
      "short": 14364,
      "net": 10259,
      "label": "Småhandlere"
    },
    "kategori": "aksjer",
    "navn_no": "Msci Emerging Mkts Index",
    "forklaring": ""
  },
  {
    "date": "2021-11-30",
    "market": "Msci Em Asia Mini Ntr Index",
    "symbol": "24477G",
    "report": "tff",
    "open_interest": 185630,
    "change_oi": 26672,
    "change_spec_net": -3715,
    "spekulanter": {
      "long": 0,
      "short": 11591,
      "net": -11591,
      "label": "Hedge Funds"
    },
    "institusjoner": {
      "long": 1272,
      "short": 0,
      "net": 1272,
      "label": "Pensjonsfond"
    },
    "meglere": {
      "long": 106522,
      "short": 97925,
      "net": 8597,
      "label": "Banker/Meglere"
    },
    "smahandlere": {
      "long": 29,
      "short": 333,
      "net": -304,
      "label": "Småhandlere"
    },
    "kategori": "aksjer",
    "navn_no": "Msci Em Asia Mini Ntr Index",
    "forklaring": ""
  },
  {
    "date": "2021-12-28",
    "market": "S&P 500 Annual Dividend Index",
    "symbol": "43874A",
    "report": "tff",
    "open_interest": 184654,
    "change_oi": 9389,
    "change_spec_net": 8472,
    "spekulanter": {
      "long": 113688,
      "short": 755,
      "net": 112933,
      "label": "Hedge Funds"
    },
    "institusjoner": {
      "long": 17485,
      "short": 5885,
      "net": 11600,
      "label": "Pensjonsfond"
    },
    "meglere": {
      "long": 23653,
      "short": 149702,
      "net": -126049,
      "label": "Banker/Meglere"
    },
    "smahandlere": {
      "long": 303,
      "short": 71,
      "net": 232,
      "label": "Småhandlere"
    },
    "kategori": "aksjer",
    "navn_no": "S&P 500 Annual Dividend Index",
    "forklaring": ""
  },
  {
    "date": "2021-12-28",
    "market": "U.S. Treasury Bonds",
    "symbol": "020601",
    "report": "tff",
    "open_interest": 1208000,
    "change_oi": -17029,
    "change_spec_net": 24273,
    "spekulanter": {
      "long": 110122,
      "short": 383330,
      "net": -273208,
      "label": "Hedge Funds"
    },
    "institusjoner": {
      "long": 552433,
      "short": 263407,
      "net": 289026,
      "label": "Pensjonsfond"
    },
    "meglere": {
      "long": 10971,
      "short": 98342,
      "net": -87371,
      "label": "Banker/Meglere"
    },
    "smahandlere": {
      "long": 185407,
      "short": 154798,
      "net": 30609,
      "label": "Småhandlere"
    },
    "kategori": "renter",
    "navn_no": "U.S. Treasury Bonds",
    "forklaring": ""
  },
  {
    "date": "2021-12-28",
    "market": "Ultra U.S. Treasury Bonds",
    "symbol": "020604",
    "report": "tff",
    "open_interest": 1248190,
    "change_oi": -6092,
    "change_spec_net": 11002,
    "spekulanter": {
      "long": 81520,
      "short": 561243,
      "net": -479723,
      "label": "Hedge Funds"
    },
    "institusjoner": {
      "long": 678511,
      "short": 276068,
      "net": 402443,
      "label": "Pensjonsfond"
    },
    "meglere": {
      "long": 36742,
      "short": 56366,
      "net": -19624,
      "label": "Banker/Meglere"
    },
    "smahandlere": {
      "long": 159612,
      "short": 123307,
      "net": 36305,
      "label": "Småhandlere"
    },
    "kategori": "renter",
    "navn_no": "Ultra U.S. Treasury Bonds",
    "forklaring": ""
  },
  {
    "date": "2021-12-28",
    "market": "2",
    "symbol": "042601",
    "report": "tff",
    "open_interest": 1966290,
    "change_oi": -3812,
    "change_spec_net": 7666,
    "spekulanter": {
      "long": 568293,
      "short": 157948,
      "net": 410345,
      "label": "Hedge Funds"
    },
    "institusjoner": {
      "long": 641164,
      "short": 659302,
      "net": -18138,
      "label": "Pensjonsfond"
    },
    "meglere": {
      "long": 51365,
      "short": 184361,
      "net": -132996,
      "label": "Banker/Meglere"
    },
    "smahandlere": {
      "long": 122956,
      "short": 184995,
      "net": -62039,
      "label": "Småhandlere"
    },
    "kategori": "renter",
    "navn_no": "2",
    "forklaring": ""
  },
  {
    "date": "2021-12-28",
    "market": "10",
    "symbol": "043602",
    "report": "tff",
    "open_interest": 3846382,
    "change_oi": 48115,
    "change_spec_net": -72155,
    "spekulanter": {
      "long": 624858,
      "short": 585680,
      "net": 39178,
      "label": "Hedge Funds"
    },
    "institusjoner": {
      "long": 1593764,
      "short": 1379451,
      "net": 214313,
      "label": "Pensjonsfond"
    },
    "meglere": {
      "long": 204907,
      "short": 152459,
      "net": 52448,
      "label": "Banker/Meglere"
    },
    "smahandlere": {
      "long": 291916,
      "short": 537085,
      "net": -245169,
      "label": "Småhandlere"
    },
    "kategori": "renter",
    "navn_no": "10",
    "forklaring": ""
  },
  {
    "date": "2021-12-28",
    "market": "Ultra 10",
    "symbol": "043607",
    "report": "tff",
    "open_interest": 1367246,
    "change_oi": 13749,
    "change_spec_net": -9407,
    "spekulanter": {
      "long": 480757,
      "short": 297236,
      "net": 183521,
      "label": "Hedge Funds"
    },
    "institusjoner": {
      "long": 396863,
      "short": 521779,
      "net": -124916,
      "label": "Pensjonsfond"
    },
    "meglere": {
      "long": 73148,
      "short": 16537,
      "net": 56611,
      "label": "Banker/Meglere"
    },
    "smahandlere": {
      "long": 119235,
      "short": 269924,
      "net": -150689,
      "label": "Småhandlere"
    },
    "kategori": "renter",
    "navn_no": "Ultra 10",
    "forklaring": ""
  },
  {
    "date": "2021-12-28",
    "market": "5",
    "symbol": "044601",
    "report": "tff",
    "open_interest": 3741327,
    "change_oi": 137275,
    "change_spec_net": -93054,
    "spekulanter": {
      "long": 170528,
      "short": 1041451,
      "net": -870923,
      "label": "Hedge Funds"
    },
    "institusjoner": {
      "long": 2085672,
      "short": 903690,
      "net": 1181982,
      "label": "Pensjonsfond"
    },
    "meglere": {
      "long": 41975,
      "short": 247401,
      "net": -205426,
      "label": "Banker/Meglere"
    },
    "smahandlere": {
      "long": 259112,
      "short": 503967,
      "net": -244855,
      "label": "Småhandlere"
    },
    "kategori": "renter",
    "navn_no": "5",
    "forklaring": ""
  },
  {
    "date": "2021-12-28",
    "market": "30",
    "symbol": "045601",
    "report": "tff",
    "open_interest": 1366900,
    "change_oi": -1642,
    "change_spec_net": 5019,
    "spekulanter": {
      "long": 38472,
      "short": 246246,
      "net": -207774,
      "label": "Hedge Funds"
    },
    "institusjoner": {
      "long": 21031,
      "short": 4968,
      "net": 16063,
      "label": "Pensjonsfond"
    },
    "meglere": {
      "long": 371072,
      "short": 185778,
      "net": 185294,
      "label": "Banker/Meglere"
    },
    "smahandlere": {
      "long": 23529,
      "short": 37678,
      "net": -14149,
      "label": "Småhandlere"
    },
    "kategori": "renter",
    "navn_no": "30",
    "forklaring": ""
  },
  {
    "date": "2021-12-28",
    "market": "3",
    "symbol": "132741",
    "report": "tff",
    "open_interest": 11150593,
    "change_oi": 44698,
    "change_spec_net": -17410,
    "spekulanter": {
      "long": 1430215,
      "short": 2621537,
      "net": -1191322,
      "label": "Hedge Funds"
    },
    "institusjoner": {
      "long": 802508,
      "short": 1432798,
      "net": -630290,
      "label": "Pensjonsfond"
    },
    "meglere": {
      "long": 3373235,
      "short": 932627,
      "net": 2440608,
      "label": "Banker/Meglere"
    },
    "smahandlere": {
      "long": 436619,
      "short": 812073,
      "net": -375454,
      "label": "Småhandlere"
    },
    "kategori": "renter",
    "navn_no": "3",
    "forklaring": ""
  },
  {
    "date": "2021-12-28",
    "market": "1",
    "symbol": "134742",
    "report": "tff",
    "open_interest": 225248,
    "change_oi": -965,
    "change_spec_net": 738,
    "spekulanter": {
      "long": 34504,
      "short": 49951,
      "net": -15447,
      "label": "Hedge Funds"
    },
    "institusjoner": {
      "long": 5588,
      "short": 2288,
      "net": 3300,
      "label": "Pensjonsfond"
    },
    "meglere": {
      "long": 89871,
      "short": 73386,
      "net": 16485,
      "label": "Banker/Meglere"
    },
    "smahandlere": {
      "long": 95,
      "short": 331,
      "net": -236,
      "label": "Småhandlere"
    },
    "kategori": "renter",
    "navn_no": "1",
    "forklaring": ""
  },
  {
    "date": "2021-12-28",
    "market": "10 Year Deliverable Ir",
    "symbol": "246605",
    "report": "tff",
    "open_interest": 106881,
    "change_oi": 1928,
    "change_spec_net": -396,
    "spekulanter": {
      "long": 7354,
      "short": 52449,
      "net": -45095,
      "label": "Hedge Funds"
    },
    "institusjoner": {
      "long": 0,
      "short": 1657,
      "net": -1657,
      "label": "Pensjonsfond"
    },
    "meglere": {
      "long": 0,
      "short": 22407,
      "net": -22407,
      "label": "Banker/Meglere"
    },
    "smahandlere": {
      "long": 0,
      "short": 50,
      "net": -50,
      "label": "Småhandlere"
    },
    "kategori": "landbruk",
    "navn_no": "10 Year Deliverable Ir",
    "forklaring": ""
  },
  {
    "date": "2021-06-01",
    "market": "5 Year Eris Swap",
    "symbol": "344601",
    "report": "tff",
    "open_interest": 39662,
    "change_oi": 0,
    "change_spec_net": 0,
    "spekulanter": {
      "long": 2222,
      "short": 8236,
      "net": -6014,
      "label": "Hedge Funds"
    },
    "institusjoner": {
      "long": 0,
      "short": 65,
      "net": -65,
      "label": "Pensjonsfond"
    },
    "meglere": {
      "long": 8301,
      "short": 581,
      "net": 7720,
      "label": "Banker/Meglere"
    },
    "smahandlere": {
      "long": 0,
      "short": 35,
      "net": -35,
      "label": "Småhandlere"
    },
    "kategori": "renter",
    "navn_no": "5 Year Eris Swap",
    "forklaring": ""
  },
  {
    "date": "2021-12-28",
    "market": "Bitcoin",
    "symbol": "133741",
    "report": "tff",
    "open_interest": 12468,
    "change_oi": -384,
    "change_spec_net": 27,
    "spekulanter": {
      "long": 2453,
      "short": 8104,
      "net": -5651,
      "label": "Hedge Funds"
    },
    "institusjoner": {
      "long": 5554,
      "short": 859,
      "net": 4695,
      "label": "Pensjonsfond"
    },
    "meglere": {
      "long": 459,
      "short": 540,
      "net": -81,
      "label": "Banker/Meglere"
    },
    "smahandlere": {
      "long": 1606,
      "short": 840,
      "net": 766,
      "label": "Småhandlere"
    },
    "kategori": "krypto",
    "navn_no": "Bitcoin (BTC)",
    "forklaring": "Verdens største kryptovaluta."
  },
  {
    "date": "2021-12-28",
    "market": "Micro Bitcoin",
    "symbol": "133742",
    "report": "tff",
    "open_interest": 41281,
    "change_oi": -1137,
    "change_spec_net": 1228,
    "spekulanter": {
      "long": 23128,
      "short": 27637,
      "net": -4509,
      "label": "Hedge Funds"
    },
    "institusjoner": {
      "long": 76,
      "short": 0,
      "net": 76,
      "label": "Pensjonsfond"
    },
    "meglere": {
      "long": 1578,
      "short": 107,
      "net": 1471,
      "label": "Banker/Meglere"
    },
    "smahandlere": {
      "long": 5882,
      "short": 1114,
      "net": 4768,
      "label": "Småhandlere"
    },
    "kategori": "krypto",
    "navn_no": "Micro Bitcoin",
    "forklaring": ""
  },
  {
    "date": "2021-12-28",
    "market": "Ether Cash Settled",
    "symbol": "146021",
    "report": "tff",
    "open_interest": 4554,
    "change_oi": -349,
    "change_spec_net": -54,
    "spekulanter": {
      "long": 1343,
      "short": 3223,
      "net": -1880,
      "label": "Hedge Funds"
    },
    "institusjoner": {
      "long": 0,
      "short": 111,
      "net": -111,
      "label": "Pensjonsfond"
    },
    "meglere": {
      "long": 160,
      "short": 40,
      "net": 120,
      "label": "Banker/Meglere"
    },
    "smahandlere": {
      "long": 1264,
      "short": 453,
      "net": 811,
      "label": "Småhandlere"
    },
    "kategori": "krypto",
    "navn_no": "Ether Cash Settled",
    "forklaring": ""
  },
  {
    "date": "2021-12-28",
    "market": "Micro Ether",
    "symbol": "146022",
    "report": "tff",
    "open_interest": 20861,
    "change_oi": 5063,
    "change_spec_net": -1485,
    "spekulanter": {
      "long": 14221,
      "short": 16992,
      "net": -2771,
      "label": "Hedge Funds"
    },
    "institusjoner": {
      "long": 0,
      "short": 0,
      "net": 0,
      "label": "Pensjonsfond"
    },
    "meglere": {
      "long": 0,
      "short": 1644,
      "net": -1644,
      "label": "Banker/Meglere"
    },
    "smahandlere": {
      "long": 1017,
      "short": 125,
      "net": 892,
      "label": "Småhandlere"
    },
    "kategori": "krypto",
    "navn_no": "Micro Ether",
    "forklaring": ""
  },
  {
    "date": "2021-12-28",
    "market": "U.S. Dollar Index",
    "symbol": "098662",
    "report": "tff",
    "open_interest": 57892,
    "change_oi": 1730,
    "change_spec_net": 453,
    "spekulanter": {
      "long": 16623,
      "short": 12614,
      "net": 4009,
      "label": "Hedge Funds"
    },
    "institusjoner": {
      "long": 24524,
      "short": 957,
      "net": 23567,
      "label": "Pensjonsfond"
    },
    "meglere": {
      "long": 1336,
      "short": 40621,
      "net": -39285,
      "label": "Banker/Meglere"
    },
    "smahandlere": {
      "long": 7471,
      "short": 1799,
      "net": 5672,
      "label": "Småhandlere"
    },
    "kategori": "annet",
    "navn_no": "U.S. Dollar Index",
    "forklaring": ""
  },
  {
    "date": "2021-12-28",
    "market": "Vix Futures",
    "symbol": "1170E1",
    "report": "tff",
    "open_interest": 277502,
    "change_oi": -11668,
    "change_spec_net": 6480,
    "spekulanter": {
      "long": 28734,
      "short": 76503,
      "net": -47769,
      "label": "Hedge Funds"
    },
    "institusjoner": {
      "long": 92416,
      "short": 62155,
      "net": 30261,
      "label": "Pensjonsfond"
    },
    "meglere": {
      "long": 37863,
      "short": 18161,
      "net": 19702,
      "label": "Banker/Meglere"
    },
    "smahandlere": {
      "long": 17818,
      "short": 26848,
      "net": -9030,
      "label": "Småhandlere"
    },
    "kategori": "aksjer",
    "navn_no": "VIX – Fryktindeks",
    "forklaring": "Høy verdi = mye usikkerhet i markedet."
  },
  {
    "date": "2021-12-28",
    "market": "Bloomberg Commodity Index",
    "symbol": "221602",
    "report": "tff",
    "open_interest": 40335,
    "change_oi": 388,
    "change_spec_net": -455,
    "spekulanter": {
      "long": 413,
      "short": 25343,
      "net": -24930,
      "label": "Hedge Funds"
    },
    "institusjoner": {
      "long": 26706,
      "short": 579,
      "net": 26127,
      "label": "Pensjonsfond"
    },
    "meglere": {
      "long": 3615,
      "short": 13210,
      "net": -9595,
      "label": "Banker/Meglere"
    },
    "smahandlere": {
      "long": 500,
      "short": 42,
      "net": 458,
      "label": "Småhandlere"
    },
    "kategori": "annet",
    "navn_no": "Bloomberg Commodity Index",
    "forklaring": ""
  }
]