{
  "DXY": {
    "horizon": "WATCHLIST",
    "dir_color": "bear",
    "score": 4.5,
    "grade": "C",
    "setup": null,
    "setup_dir": "short",
    "created": "2026-04-16T08:43"
  },
  "EURUSD": {
    "horizon": "WATCHLIST",
    "dir_color": "bull",
    "score": 5.0,
    "grade": "C",
    "setup": null,
    "setup_dir": "long",
    "created": "2026-04-16T08:43"
  },
  "USDJPY": {
    "horizon": "WATCHLIST",
    "dir_color": "bull",
    "score": 2.5,
    "grade": "C",
    "setup": null,
    "setup_dir": "long",
    "created": "2026-04-16T08:43"
  },
  "GBPUSD": {
    "horizon": "WATCHLIST",
    "dir_color": "bull",
    "score": 4.5,
    "grade": "C",
    "setup": null,
    "setup_dir": "long",
    "created": "2026-04-16T08:43"
  },
  "AUDUSD": {
    "horizon": "WATCHLIST",
    "dir_color": "bull",
    "score": 5.0,
    "grade": "C",
    "setup": null,
    "setup_dir": "long",
    "created": "2026-04-16T08:43"
  },
  "Gold": {
    "horizon": "WATCHLIST",
    "dir_color": "bull",
    "score": 4.5,
    "grade": "C",
    "setup": null,
    "setup_dir": "long",
    "created": "2026-04-16T08:43"
  },
  "Silver": {
    "horizon": "WATCHLIST",
    "dir_color": "bull",
    "score": 8.0,
    "grade": "C",
    "setup": null,
    "setup_dir": "long",
    "created": "2026-04-16T08:43"
  },
  "Brent": {
    "horizon": "WATCHLIST",
    "dir_color": "bull",
    "score": 4.0,
    "grade": "C",
    "setup": null,
    "setup_dir": "long",
    "created": "2026-04-16T08:43"
  },
  "WTI": {
    "horizon": "WATCHLIST",
    "dir_color": "bull",
    "score": 4.0,
    "grade": "C",
    "setup": null,
    "setup_dir": "long",
    "created": "2026-04-16T08:43"
  },
  "SPX": {
    "horizon": "WATCHLIST",
    "dir_color": "bull",
    "score": 5.0,
    "grade": "C",
    "setup": null,
    "setup_dir": "long",
    "created": "2026-04-16T08:43"
  },
  "NAS100": {
    "horizon": "WATCHLIST",
    "dir_color": "bull",
    "score": 4.0,
    "grade": "C",
    "setup": null,
    "setup_dir": "long",
    "created": "2026-04-16T08:43"
  }
}