{"symbol": "006NHY", "market": "Tx Rec Crs V26 Front Half", "navn_no": "Tx Rec Crs V26 Front Half", "kategori": "annet", "report": "disaggregated", "data": [{"date": "2022-12-27", "spec_net": -75, "spec_long": 0, "spec_short": 75, "oi": 2655}, {"date": "2023-12-26", "spec_net": -75, "spec_long": 0, "spec_short": 75, "oi": 3311}, {"date": "2024-12-31", "spec_net": -75, "spec_long": 0, "spec_short": 75, "oi": 5657}, {"date": "2025-12-30", "spec_net": 0, "spec_long": 0, "spec_short": 0, "oi": 8118}]}