{"symbol": "06465M", "market": "Pjm Cal Month Off Pk Lmp Swap", "navn_no": "Pjm Cal Month Off Pk Lmp Swap", "kategori": "renter", "report": "disaggregated", "data": [{"date": "", "spec_net": -1600, "spec_long": 0, "spec_short": 1600, "oi": 31966}, {"date": "", "spec_net": -1892, "spec_long": 568, "spec_short": 2460, "oi": 28746}, {"date": "", "spec_net": -1014, "spec_long": 66, "spec_short": 1080, "oi": 18588}, {"date": "2013-12-31", "spec_net": -728, "spec_long": 0, "spec_short": 728, "oi": 12291}, {"date": "2014-07-15", "spec_net": -168, "spec_long": 0, "spec_short": 168, "oi": 10262}]}