{
  "generated": "2026-04-10 22:00 UTC",
  "source": "ICE Futures Europe",
  "markets": [
    {
      "market": "ice gasoil",
      "display_name": "Ice Gasoil",
      "spekulanter": {
        "long": 93984,
        "short": 29847,
        "net": 64137,
        "label": "Managed Money"
      },
      "open_interest": 840208,
      "change_spec_net": -10997,
      "spec_net_history": [
        75134,
        64137
      ],
      "date": "2026-04-07",
      "report": "ice"
    },
    {
      "market": "ice brent crude",
      "display_name": "Ice Brent Crude",
      "spekulanter": {
        "long": 425195,
        "short": 50469,
        "net": 374726,
        "label": "Managed Money"
      },
      "open_interest": 2952647,
      "change_spec_net": 58896,
      "spec_net_history": [
        315830,
        374726
      ],
      "date": "2026-04-07",
      "report": "ice"
    }
  ]
}